[
  {
    "Date":"2024-09-26T00:00:00.000",
    "Code":"245A",
    "Open":2700.0,
    "High":2927.0,
    "Low":2625.0,
    "Close":2700.0,
    "UpperLimit":"0",
    "LowerLimit":"0",
    "Volume":2127400.0,
    "TurnoverValue":"5867610300.0",
    "AdjustmentFactor":"1.0",
    "AdjustmentOpen":"2700.0",
    "AdjustmentHigh":"2927.0",
    "AdjustmentLow":"2625.0",
    "AdjustmentClose":"2700.0",
    "AdjustmentVolume":"2127400.0"
  },
  {
    "Date":"2024-09-27T00:00:00.000",
    "Code":"245A",
    "Open":2900.0,
    "High":3200.0,
    "Low":2688.0,
    "Close":2888.0,
    "UpperLimit":"1",
    "LowerLimit":"0",
    "Volume":1790200.0,
    "TurnoverValue":"5388811200.0",
    "AdjustmentFactor":"1.0",
    "AdjustmentOpen":"2900.0",
    "AdjustmentHigh":"3200.0",
    "AdjustmentLow":"2688.0",
    "AdjustmentClose":"2888.0",
    "AdjustmentVolume":"1790200.0"
  },
  {
    "Date":"2024-09-30T00:00:00.000",
    "Code":"245A",
    "Open":2830.0,
    "High":2869.0,
    "Low":2720.0,
    "Close":2830.0,
    "UpperLimit":"0",
    "LowerLimit":"0",
    "Volume":151000.0,
    "TurnoverValue":"423730100.0",
    "AdjustmentFactor":"1.0",
    "AdjustmentOpen":"2830.0",
    "AdjustmentHigh":"2869.0",
    "AdjustmentLow":"2720.0",
    "AdjustmentClose":"2830.0",
    "AdjustmentVolume":"151000.0"
  },
  {
    "Date":"2024-10-01T00:00:00.000",
    "Code":"245A",
    "Open":2873.0,
    "High":3085.0,
    "Low":2813.0,
    "Close":2850.0,
    "UpperLimit":"0",
    "LowerLimit":"0",
    "Volume":149700.0,
    "TurnoverValue":"435369200.0",
    "AdjustmentFactor":"1.0",
    "AdjustmentOpen":"2873.0",
    "AdjustmentHigh":"3085.0",
    "AdjustmentLow":"2813.0",
    "AdjustmentClose":"2850.0",
    "AdjustmentVolume":"149700.0"
  },
  {
    "Date":"2024-10-02T00:00:00.000",
    "Code":"245A",
    "Open":2800.0,
    "High":2871.0,
    "Low":2780.0,
    "Close":2780.0,
    "UpperLimit":"0",
    "LowerLimit":"0",
    "Volume":71300.0,
    "TurnoverValue":"200617000.0",
    "AdjustmentFactor":"1.0",
    "AdjustmentOpen":"2800.0",
    "AdjustmentHigh":"2871.0",
    "AdjustmentLow":"2780.0",
    "AdjustmentClose":"2780.0",
    "AdjustmentVolume":"71300.0"
  },
  {
    "Date":"2024-10-03T00:00:00.000",
    "Code":"245A",
    "Open":2815.0,
    "High":2828.0,
    "Low":2680.0,
    "Close":2745.0,
    "UpperLimit":"0",
    "LowerLimit":"0",
    "Volume":85400.0,
    "TurnoverValue":"233628700.0",
    "AdjustmentFactor":"1.0",
    "AdjustmentOpen":"2815.0",
    "AdjustmentHigh":"2828.0",
    "AdjustmentLow":"2680.0",
    "AdjustmentClose":"2745.0",
    "AdjustmentVolume":"85400.0"
  },
  {
    "Date":"2024-10-04T00:00:00.000",
    "Code":"245A",
    "Open":2745.0,
    "High":2800.0,
    "Low":2725.0,
    "Close":2785.0,
    "UpperLimit":"0",
    "LowerLimit":"0",
    "Volume":39700.0,
    "TurnoverValue":"109670600.0",
    "AdjustmentFactor":"1.0",
    "AdjustmentOpen":"2745.0",
    "AdjustmentHigh":"2800.0",
    "AdjustmentLow":"2725.0",
    "AdjustmentClose":"2785.0",
    "AdjustmentVolume":"39700.0"
  },
  {
    "Date":"2024-10-07T00:00:00.000",
    "Code":"245A",
    "Open":2830.0,
    "High":2886.0,
    "Low":2818.0,
    "Close":2866.0,
    "UpperLimit":"0",
    "LowerLimit":"0",
    "Volume":46500.0,
    "TurnoverValue":"132888300.0",
    "AdjustmentFactor":"1.0",
    "AdjustmentOpen":"2830.0",
    "AdjustmentHigh":"2886.0",
    "AdjustmentLow":"2818.0",
    "AdjustmentClose":"2866.0",
    "AdjustmentVolume":"46500.0"
  },
  {
    "Date":"2024-10-08T00:00:00.000",
    "Code":"245A",
    "Open":2830.0,
    "High":2858.0,
    "Low":2797.0,
    "Close":2831.0,
    "UpperLimit":"0",
    "LowerLimit":"0",
    "Volume":28300.0,
    "TurnoverValue":"79823400.0",
    "AdjustmentFactor":"1.0",
    "AdjustmentOpen":"2830.0",
    "AdjustmentHigh":"2858.0",
    "AdjustmentLow":"2797.0",
    "AdjustmentClose":"2831.0",
    "AdjustmentVolume":"28300.0"
  },
  {
    "Date":"2024-10-09T00:00:00.000",
    "Code":"245A",
    "Open":2828.0,
    "High":2890.0,
    "Low":2812.0,
    "Close":2890.0,
    "UpperLimit":"0",
    "LowerLimit":"0",
    "Volume":17100.0,
    "TurnoverValue":"48677200.0",
    "AdjustmentFactor":"1.0",
    "AdjustmentOpen":"2828.0",
    "AdjustmentHigh":"2890.0",
    "AdjustmentLow":"2812.0",
    "AdjustmentClose":"2890.0",
    "AdjustmentVolume":"17100.0"
  },
  {
    "Date":"2024-10-10T00:00:00.000",
    "Code":"245A",
    "Open":2900.0,
    "High":2998.0,
    "Low":2897.0,
    "Close":2975.0,
    "UpperLimit":"0",
    "LowerLimit":"0",
    "Volume":28300.0,
    "TurnoverValue":"83485000.0",
    "AdjustmentFactor":"1.0",
    "AdjustmentOpen":"2900.0",
    "AdjustmentHigh":"2998.0",
    "AdjustmentLow":"2897.0",
    "AdjustmentClose":"2975.0",
    "AdjustmentVolume":"28300.0"
  },
  {
    "Date":"2024-10-11T00:00:00.000",
    "Code":"245A",
    "Open":2960.0,
    "High":2976.0,
    "Low":2911.0,
    "Close":2911.0,
    "UpperLimit":"0",
    "LowerLimit":"0",
    "Volume":9900.0,
    "TurnoverValue":"29117800.0",
    "AdjustmentFactor":"1.0",
    "AdjustmentOpen":"2960.0",
    "AdjustmentHigh":"2976.0",
    "AdjustmentLow":"2911.0",
    "AdjustmentClose":"2911.0",
    "AdjustmentVolume":"9900.0"
  },
  {
    "Date":"2024-10-15T00:00:00.000",
    "Code":"245A",
    "Open":2943.0,
    "High":2943.0,
    "Low":2840.0,
    "Close":2900.0,
    "UpperLimit":"0",
    "LowerLimit":"0",
    "Volume":53500.0,
    "TurnoverValue":"155165600.0",
    "AdjustmentFactor":"1.0",
    "AdjustmentOpen":"2943.0",
    "AdjustmentHigh":"2943.0",
    "AdjustmentLow":"2840.0",
    "AdjustmentClose":"2900.0",
    "AdjustmentVolume":"53500.0"
  },
  {
    "Date":"2024-10-16T00:00:00.000",
    "Code":"245A",
    "Open":2650.0,
    "High":2711.0,
    "Low":2452.0,
    "Close":2480.0,
    "UpperLimit":"0",
    "LowerLimit":"0",
    "Volume":242500.0,
    "TurnoverValue":"613588100.0",
    "AdjustmentFactor":"1.0",
    "AdjustmentOpen":"2650.0",
    "AdjustmentHigh":"2711.0",
    "AdjustmentLow":"2452.0",
    "AdjustmentClose":"2480.0",
    "AdjustmentVolume":"242500.0"
  },
  {
    "Date":"2024-10-17T00:00:00.000",
    "Code":"245A",
    "Open":2470.0,
    "High":2499.0,
    "Low":2425.0,
    "Close":2432.0,
    "UpperLimit":"0",
    "LowerLimit":"0",
    "Volume":43200.0,
    "TurnoverValue":"106072100.0",
    "AdjustmentFactor":"1.0",
    "AdjustmentOpen":"2470.0",
    "AdjustmentHigh":"2499.0",
    "AdjustmentLow":"2425.0",
    "AdjustmentClose":"2432.0",
    "AdjustmentVolume":"43200.0"
  },
  {
    "Date":"2024-10-18T00:00:00.000",
    "Code":"245A",
    "Open":2430.0,
    "High":2430.0,
    "Low":2329.0,
    "Close":2355.0,
    "UpperLimit":"0",
    "LowerLimit":"0",
    "Volume":63800.0,
    "TurnoverValue":"150889700.0",
    "AdjustmentFactor":"1.0",
    "AdjustmentOpen":"2430.0",
    "AdjustmentHigh":"2430.0",
    "AdjustmentLow":"2329.0",
    "AdjustmentClose":"2355.0",
    "AdjustmentVolume":"63800.0"
  },
  {
    "Date":"2024-10-21T00:00:00.000",
    "Code":"245A",
    "Open":2355.0,
    "High":2419.0,
    "Low":2326.0,
    "Close":2412.0,
    "UpperLimit":"0",
    "LowerLimit":"0",
    "Volume":16800.0,
    "TurnoverValue":"39964600.0",
    "AdjustmentFactor":"1.0",
    "AdjustmentOpen":"2355.0",
    "AdjustmentHigh":"2419.0",
    "AdjustmentLow":"2326.0",
    "AdjustmentClose":"2412.0",
    "AdjustmentVolume":"16800.0"
  },
  {
    "Date":"2024-10-22T00:00:00.000",
    "Code":"245A",
    "Open":2412.0,
    "High":2412.0,
    "Low":2215.0,
    "Close":2265.0,
    "UpperLimit":"0",
    "LowerLimit":"0",
    "Volume":47100.0,
    "TurnoverValue":"107138400.0",
    "AdjustmentFactor":"1.0",
    "AdjustmentOpen":"2412.0",
    "AdjustmentHigh":"2412.0",
    "AdjustmentLow":"2215.0",
    "AdjustmentClose":"2265.0",
    "AdjustmentVolume":"47100.0"
  },
  {
    "Date":"2024-10-23T00:00:00.000",
    "Code":"245A",
    "Open":2270.0,
    "High":2296.0,
    "Low":2163.0,
    "Close":2177.0,
    "UpperLimit":"0",
    "LowerLimit":"0",
    "Volume":46100.0,
    "TurnoverValue":"101366400.0",
    "AdjustmentFactor":"1.0",
    "AdjustmentOpen":"2270.0",
    "AdjustmentHigh":"2296.0",
    "AdjustmentLow":"2163.0",
    "AdjustmentClose":"2177.0",
    "AdjustmentVolume":"46100.0"
  },
  {
    "Date":"2024-10-24T00:00:00.000",
    "Code":"245A",
    "Open":2155.0,
    "High":2183.0,
    "Low":2128.0,
    "Close":2130.0,
    "UpperLimit":"0",
    "LowerLimit":"0",
    "Volume":21900.0,
    "TurnoverValue":"47174300.0",
    "AdjustmentFactor":"1.0",
    "AdjustmentOpen":"2155.0",
    "AdjustmentHigh":"2183.0",
    "AdjustmentLow":"2128.0",
    "AdjustmentClose":"2130.0",
    "AdjustmentVolume":"21900.0"
  },
  {
    "Date":"2024-10-25T00:00:00.000",
    "Code":"245A",
    "Open":2129.0,
    "High":2183.0,
    "Low":2074.0,
    "Close":2178.0,
    "UpperLimit":"0",
    "LowerLimit":"0",
    "Volume":29400.0,
    "TurnoverValue":"62698000.0",
    "AdjustmentFactor":"1.0",
    "AdjustmentOpen":"2129.0",
    "AdjustmentHigh":"2183.0",
    "AdjustmentLow":"2074.0",
    "AdjustmentClose":"2178.0",
    "AdjustmentVolume":"29400.0"
  },
  {
    "Date":"2024-10-28T00:00:00.000",
    "Code":"245A",
    "Open":2167.0,
    "High":2291.0,
    "Low":2167.0,
    "Close":2287.0,
    "UpperLimit":"0",
    "LowerLimit":"0",
    "Volume":15000.0,
    "TurnoverValue":"33620400.0",
    "AdjustmentFactor":"1.0",
    "AdjustmentOpen":"2167.0",
    "AdjustmentHigh":"2291.0",
    "AdjustmentLow":"2167.0",
    "AdjustmentClose":"2287.0",
    "AdjustmentVolume":"15000.0"
  },
  {
    "Date":"2024-10-29T00:00:00.000",
    "Code":"245A",
    "Open":2297.0,
    "High":2338.0,
    "Low":2262.0,
    "Close":2306.0,
    "UpperLimit":"0",
    "LowerLimit":"0",
    "Volume":16500.0,
    "TurnoverValue":"37928900.0",
    "AdjustmentFactor":"1.0",
    "AdjustmentOpen":"2297.0",
    "AdjustmentHigh":"2338.0",
    "AdjustmentLow":"2262.0",
    "AdjustmentClose":"2306.0",
    "AdjustmentVolume":"16500.0"
  },
  {
    "Date":"2024-10-30T00:00:00.000",
    "Code":"245A",
    "Open":2302.0,
    "High":2306.0,
    "Low":2246.0,
    "Close":2256.0,
    "UpperLimit":"0",
    "LowerLimit":"0",
    "Volume":12300.0,
    "TurnoverValue":"27939300.0",
    "AdjustmentFactor":"1.0",
    "AdjustmentOpen":"2302.0",
    "AdjustmentHigh":"2306.0",
    "AdjustmentLow":"2246.0",
    "AdjustmentClose":"2256.0",
    "AdjustmentVolume":"12300.0"
  },
  {
    "Date":"2024-10-31T00:00:00.000",
    "Code":"245A",
    "Open":2240.0,
    "High":2290.0,
    "Low":2240.0,
    "Close":2277.0,
    "UpperLimit":"0",
    "LowerLimit":"0",
    "Volume":4000.0,
    "TurnoverValue":"9061500.0",
    "AdjustmentFactor":"1.0",
    "AdjustmentOpen":"2240.0",
    "AdjustmentHigh":"2290.0",
    "AdjustmentLow":"2240.0",
    "AdjustmentClose":"2277.0",
    "AdjustmentVolume":"4000.0"
  },
  {
    "Date":"2024-11-01T00:00:00.000",
    "Code":"245A",
    "Open":2254.0,
    "High":2269.0,
    "Low":2206.0,
    "Close":2230.0,
    "UpperLimit":"0",
    "LowerLimit":"0",
    "Volume":13800.0,
    "TurnoverValue":"30736700.0",
    "AdjustmentFactor":"1.0",
    "AdjustmentOpen":"2254.0",
    "AdjustmentHigh":"2269.0",
    "AdjustmentLow":"2206.0",
    "AdjustmentClose":"2230.0",
    "AdjustmentVolume":"13800.0"
  },
  {
    "Date":"2024-11-05T00:00:00.000",
    "Code":"245A",
    "Open":2222.0,
    "High":2249.0,
    "Low":2201.0,
    "Close":2201.0,
    "UpperLimit":"0",
    "LowerLimit":"0",
    "Volume":8400.0,
    "TurnoverValue":"18644500.0",
    "AdjustmentFactor":"1.0",
    "AdjustmentOpen":"2222.0",
    "AdjustmentHigh":"2249.0",
    "AdjustmentLow":"2201.0",
    "AdjustmentClose":"2201.0",
    "AdjustmentVolume":"8400.0"
  },
  {
    "Date":"2024-11-06T00:00:00.000",
    "Code":"245A",
    "Open":2201.0,
    "High":2246.0,
    "Low":2188.0,
    "Close":2204.0,
    "UpperLimit":"0",
    "LowerLimit":"0",
    "Volume":8100.0,
    "TurnoverValue":"17832400.0",
    "AdjustmentFactor":"1.0",
    "AdjustmentOpen":"2201.0",
    "AdjustmentHigh":"2246.0",
    "AdjustmentLow":"2188.0",
    "AdjustmentClose":"2204.0",
    "AdjustmentVolume":"8100.0"
  },
  {
    "Date":"2024-11-07T00:00:00.000",
    "Code":"245A",
    "Open":2194.0,
    "High":2206.0,
    "Low":2125.0,
    "Close":2141.0,
    "UpperLimit":"0",
    "LowerLimit":"0",
    "Volume":19300.0,
    "TurnoverValue":"41507700.0",
    "AdjustmentFactor":"1.0",
    "AdjustmentOpen":"2194.0",
    "AdjustmentHigh":"2206.0",
    "AdjustmentLow":"2125.0",
    "AdjustmentClose":"2141.0",
    "AdjustmentVolume":"19300.0"
  },
  {
    "Date":"2024-11-08T00:00:00.000",
    "Code":"245A",
    "Open":2129.0,
    "High":2161.0,
    "Low":2125.0,
    "Close":2128.0,
    "UpperLimit":"0",
    "LowerLimit":"0",
    "Volume":6600.0,
    "TurnoverValue":"14076200.0",
    "AdjustmentFactor":"1.0",
    "AdjustmentOpen":"2129.0",
    "AdjustmentHigh":"2161.0",
    "AdjustmentLow":"2125.0",
    "AdjustmentClose":"2128.0",
    "AdjustmentVolume":"6600.0"
  },
  {
    "Date":"2024-11-11T00:00:00.000",
    "Code":"245A",
    "Open":2126.0,
    "High":2135.0,
    "Low":2065.0,
    "Close":2108.0,
    "UpperLimit":"0",
    "LowerLimit":"0",
    "Volume":27400.0,
    "TurnoverValue":"57341400.0",
    "AdjustmentFactor":"1.0",
    "AdjustmentOpen":"2126.0",
    "AdjustmentHigh":"2135.0",
    "AdjustmentLow":"2065.0",
    "AdjustmentClose":"2108.0",
    "AdjustmentVolume":"27400.0"
  },
  {
    "Date":"2024-11-12T00:00:00.000",
    "Code":"245A",
    "Open":2082.0,
    "High":2158.0,
    "Low":2082.0,
    "Close":2115.0,
    "UpperLimit":"0",
    "LowerLimit":"0",
    "Volume":9100.0,
    "TurnoverValue":"19265400.0",
    "AdjustmentFactor":"1.0",
    "AdjustmentOpen":"2082.0",
    "AdjustmentHigh":"2158.0",
    "AdjustmentLow":"2082.0",
    "AdjustmentClose":"2115.0",
    "AdjustmentVolume":"9100.0"
  },
  {
    "Date":"2024-11-13T00:00:00.000",
    "Code":"245A",
    "Open":2103.0,
    "High":2174.0,
    "Low":2101.0,
    "Close":2174.0,
    "UpperLimit":"0",
    "LowerLimit":"0",
    "Volume":6400.0,
    "TurnoverValue":"13616600.0",
    "AdjustmentFactor":"1.0",
    "AdjustmentOpen":"2103.0",
    "AdjustmentHigh":"2174.0",
    "AdjustmentLow":"2101.0",
    "AdjustmentClose":"2174.0",
    "AdjustmentVolume":"6400.0"
  },
  {
    "Date":"2024-11-14T00:00:00.000",
    "Code":"245A",
    "Open":2135.0,
    "High":2201.0,
    "Low":2114.0,
    "Close":2150.0,
    "UpperLimit":"0",
    "LowerLimit":"0",
    "Volume":17600.0,
    "TurnoverValue":"37866500.0",
    "AdjustmentFactor":"1.0",
    "AdjustmentOpen":"2135.0",
    "AdjustmentHigh":"2201.0",
    "AdjustmentLow":"2114.0",
    "AdjustmentClose":"2150.0",
    "AdjustmentVolume":"17600.0"
  },
  {
    "Date":"2024-11-15T00:00:00.000",
    "Code":"245A",
    "Open":2190.0,
    "High":2202.0,
    "Low":2156.0,
    "Close":2158.0,
    "UpperLimit":"0",
    "LowerLimit":"0",
    "Volume":4500.0,
    "TurnoverValue":"9793200.0",
    "AdjustmentFactor":"1.0",
    "AdjustmentOpen":"2190.0",
    "AdjustmentHigh":"2202.0",
    "AdjustmentLow":"2156.0",
    "AdjustmentClose":"2158.0",
    "AdjustmentVolume":"4500.0"
  },
  {
    "Date":"2024-11-18T00:00:00.000",
    "Code":"245A",
    "Open":2164.0,
    "High":2326.0,
    "Low":2161.0,
    "Close":2326.0,
    "UpperLimit":"0",
    "LowerLimit":"0",
    "Volume":11300.0,
    "TurnoverValue":"25694900.0",
    "AdjustmentFactor":"1.0",
    "AdjustmentOpen":"2164.0",
    "AdjustmentHigh":"2326.0",
    "AdjustmentLow":"2161.0",
    "AdjustmentClose":"2326.0",
    "AdjustmentVolume":"11300.0"
  },
  {
    "Date":"2024-11-19T00:00:00.000",
    "Code":"245A",
    "Open":2369.0,
    "High":2384.0,
    "Low":2282.0,
    "Close":2282.0,
    "UpperLimit":"0",
    "LowerLimit":"0",
    "Volume":6200.0,
    "TurnoverValue":"14391100.0",
    "AdjustmentFactor":"1.0",
    "AdjustmentOpen":"2369.0",
    "AdjustmentHigh":"2384.0",
    "AdjustmentLow":"2282.0",
    "AdjustmentClose":"2282.0",
    "AdjustmentVolume":"6200.0"
  },
  {
    "Date":"2024-11-20T00:00:00.000",
    "Code":"245A",
    "Open":2302.0,
    "High":2317.0,
    "Low":2280.0,
    "Close":2317.0,
    "UpperLimit":"0",
    "LowerLimit":"0",
    "Volume":4900.0,
    "TurnoverValue":"11235900.0",
    "AdjustmentFactor":"1.0",
    "AdjustmentOpen":"2302.0",
    "AdjustmentHigh":"2317.0",
    "AdjustmentLow":"2280.0",
    "AdjustmentClose":"2317.0",
    "AdjustmentVolume":"4900.0"
  },
  {
    "Date":"2024-11-21T00:00:00.000",
    "Code":"245A",
    "Open":2316.0,
    "High":2437.0,
    "Low":2296.0,
    "Close":2420.0,
    "UpperLimit":"0",
    "LowerLimit":"0",
    "Volume":9200.0,
    "TurnoverValue":"21924200.0",
    "AdjustmentFactor":"1.0",
    "AdjustmentOpen":"2316.0",
    "AdjustmentHigh":"2437.0",
    "AdjustmentLow":"2296.0",
    "AdjustmentClose":"2420.0",
    "AdjustmentVolume":"9200.0"
  },
  {
    "Date":"2024-11-22T00:00:00.000",
    "Code":"245A",
    "Open":2381.0,
    "High":2435.0,
    "Low":2381.0,
    "Close":2412.0,
    "UpperLimit":"0",
    "LowerLimit":"0",
    "Volume":5600.0,
    "TurnoverValue":"13477300.0",
    "AdjustmentFactor":"1.0",
    "AdjustmentOpen":"2381.0",
    "AdjustmentHigh":"2435.0",
    "AdjustmentLow":"2381.0",
    "AdjustmentClose":"2412.0",
    "AdjustmentVolume":"5600.0"
  },
  {
    "Date":"2024-11-25T00:00:00.000",
    "Code":"245A",
    "Open":2390.0,
    "High":2434.0,
    "Low":2366.0,
    "Close":2366.0,
    "UpperLimit":"0",
    "LowerLimit":"0",
    "Volume":6700.0,
    "TurnoverValue":"15956400.0",
    "AdjustmentFactor":"1.0",
    "AdjustmentOpen":"2390.0",
    "AdjustmentHigh":"2434.0",
    "AdjustmentLow":"2366.0",
    "AdjustmentClose":"2366.0",
    "AdjustmentVolume":"6700.0"
  },
  {
    "Date":"2024-11-26T00:00:00.000",
    "Code":"245A",
    "Open":2364.0,
    "High":2382.0,
    "Low":2283.0,
    "Close":2320.0,
    "UpperLimit":"0",
    "LowerLimit":"0",
    "Volume":8900.0,
    "TurnoverValue":"20707500.0",
    "AdjustmentFactor":"1.0",
    "AdjustmentOpen":"2364.0",
    "AdjustmentHigh":"2382.0",
    "AdjustmentLow":"2283.0",
    "AdjustmentClose":"2320.0",
    "AdjustmentVolume":"8900.0"
  },
  {
    "Date":"2024-11-27T00:00:00.000",
    "Code":"245A",
    "Open":2320.0,
    "High":2320.0,
    "Low":2287.0,
    "Close":2287.0,
    "UpperLimit":"0",
    "LowerLimit":"0",
    "Volume":1300.0,
    "TurnoverValue":"2983600.0",
    "AdjustmentFactor":"1.0",
    "AdjustmentOpen":"2320.0",
    "AdjustmentHigh":"2320.0",
    "AdjustmentLow":"2287.0",
    "AdjustmentClose":"2287.0",
    "AdjustmentVolume":"1300.0"
  },
  {
    "Date":"2024-11-28T00:00:00.000",
    "Code":"245A",
    "Open":2294.0,
    "High":2359.0,
    "Low":2260.0,
    "Close":2290.0,
    "UpperLimit":"0",
    "LowerLimit":"0",
    "Volume":7200.0,
    "TurnoverValue":"16535100.0",
    "AdjustmentFactor":"1.0",
    "AdjustmentOpen":"2294.0",
    "AdjustmentHigh":"2359.0",
    "AdjustmentLow":"2260.0",
    "AdjustmentClose":"2290.0",
    "AdjustmentVolume":"7200.0"
  },
  {
    "Date":"2024-11-29T00:00:00.000",
    "Code":"245A",
    "Open":2267.0,
    "High":2358.0,
    "Low":2267.0,
    "Close":2276.0,
    "UpperLimit":"0",
    "LowerLimit":"0",
    "Volume":5400.0,
    "TurnoverValue":"12471300.0",
    "AdjustmentFactor":"1.0",
    "AdjustmentOpen":"2267.0",
    "AdjustmentHigh":"2358.0",
    "AdjustmentLow":"2267.0",
    "AdjustmentClose":"2276.0",
    "AdjustmentVolume":"5400.0"
  },
  {
    "Date":"2024-12-02T00:00:00.000",
    "Code":"245A",
    "Open":2300.0,
    "High":2300.0,
    "Low":2276.0,
    "Close":2276.0,
    "UpperLimit":"0",
    "LowerLimit":"0",
    "Volume":1400.0,
    "TurnoverValue":"3195600.0",
    "AdjustmentFactor":"1.0",
    "AdjustmentOpen":"2300.0",
    "AdjustmentHigh":"2300.0",
    "AdjustmentLow":"2276.0",
    "AdjustmentClose":"2276.0",
    "AdjustmentVolume":"1400.0"
  },
  {
    "Date":"2024-12-03T00:00:00.000",
    "Code":"245A",
    "Open":2380.0,
    "High":2443.0,
    "Low":2313.0,
    "Close":2336.0,
    "UpperLimit":"0",
    "LowerLimit":"0",
    "Volume":61600.0,
    "TurnoverValue":"146850500.0",
    "AdjustmentFactor":"1.0",
    "AdjustmentOpen":"2380.0",
    "AdjustmentHigh":"2443.0",
    "AdjustmentLow":"2313.0",
    "AdjustmentClose":"2336.0",
    "AdjustmentVolume":"61600.0"
  },
  {
    "Date":"2024-12-04T00:00:00.000",
    "Code":"245A",
    "Open":2340.0,
    "High":2460.0,
    "Low":2340.0,
    "Close":2460.0,
    "UpperLimit":"0",
    "LowerLimit":"0",
    "Volume":3600.0,
    "TurnoverValue":"8703900.0",
    "AdjustmentFactor":"1.0",
    "AdjustmentOpen":"2340.0",
    "AdjustmentHigh":"2460.0",
    "AdjustmentLow":"2340.0",
    "AdjustmentClose":"2460.0",
    "AdjustmentVolume":"3600.0"
  },
  {
    "Date":"2024-12-05T00:00:00.000",
    "Code":"245A",
    "Open":2470.0,
    "High":2486.0,
    "Low":2418.0,
    "Close":2430.0,
    "UpperLimit":"0",
    "LowerLimit":"0",
    "Volume":7100.0,
    "TurnoverValue":"17464300.0",
    "AdjustmentFactor":"1.0",
    "AdjustmentOpen":"2470.0",
    "AdjustmentHigh":"2486.0",
    "AdjustmentLow":"2418.0",
    "AdjustmentClose":"2430.0",
    "AdjustmentVolume":"7100.0"
  },
  {
    "Date":"2024-12-06T00:00:00.000",
    "Code":"245A",
    "Open":2468.0,
    "High":2468.0,
    "Low":2440.0,
    "Close":2440.0,
    "UpperLimit":"0",
    "LowerLimit":"0",
    "Volume":600.0,
    "TurnoverValue":"1470600.0",
    "AdjustmentFactor":"1.0",
    "AdjustmentOpen":"2468.0",
    "AdjustmentHigh":"2468.0",
    "AdjustmentLow":"2440.0",
    "AdjustmentClose":"2440.0",
    "AdjustmentVolume":"600.0"
  },
  {
    "Date":"2024-12-09T00:00:00.000",
    "Code":"245A",
    "Open":2441.0,
    "High":2478.0,
    "Low":2441.0,
    "Close":2461.0,
    "UpperLimit":"0",
    "LowerLimit":"0",
    "Volume":2800.0,
    "TurnoverValue":"6906300.0",
    "AdjustmentFactor":"1.0",
    "AdjustmentOpen":"2441.0",
    "AdjustmentHigh":"2478.0",
    "AdjustmentLow":"2441.0",
    "AdjustmentClose":"2461.0",
    "AdjustmentVolume":"2800.0"
  },
  {
    "Date":"2024-12-10T00:00:00.000",
    "Code":"245A",
    "Open":2500.0,
    "High":2610.0,
    "Low":2478.0,
    "Close":2575.0,
    "UpperLimit":"0",
    "LowerLimit":"0",
    "Volume":56900.0,
    "TurnoverValue":"142752700.0",
    "AdjustmentFactor":"1.0",
    "AdjustmentOpen":"2500.0",
    "AdjustmentHigh":"2610.0",
    "AdjustmentLow":"2478.0",
    "AdjustmentClose":"2575.0",
    "AdjustmentVolume":"56900.0"
  },
  {
    "Date":"2024-12-11T00:00:00.000",
    "Code":"245A",
    "Open":2600.0,
    "High":2609.0,
    "Low":2548.0,
    "Close":2550.0,
    "UpperLimit":"0",
    "LowerLimit":"0",
    "Volume":37600.0,
    "TurnoverValue":"97580700.0",
    "AdjustmentFactor":"1.0",
    "AdjustmentOpen":"2600.0",
    "AdjustmentHigh":"2609.0",
    "AdjustmentLow":"2548.0",
    "AdjustmentClose":"2550.0",
    "AdjustmentVolume":"37600.0"
  },
  {
    "Date":"2024-12-12T00:00:00.000",
    "Code":"245A",
    "Open":2555.0,
    "High":2579.0,
    "Low":2532.0,
    "Close":2540.0,
    "UpperLimit":"0",
    "LowerLimit":"0",
    "Volume":2800.0,
    "TurnoverValue":"7151000.0",
    "AdjustmentFactor":"1.0",
    "AdjustmentOpen":"2555.0",
    "AdjustmentHigh":"2579.0",
    "AdjustmentLow":"2532.0",
    "AdjustmentClose":"2540.0",
    "AdjustmentVolume":"2800.0"
  },
  {
    "Date":"2024-12-13T00:00:00.000",
    "Code":"245A",
    "Open":2558.0,
    "High":2598.0,
    "Low":2558.0,
    "Close":2560.0,
    "UpperLimit":"0",
    "LowerLimit":"0",
    "Volume":3000.0,
    "TurnoverValue":"7694400.0",
    "AdjustmentFactor":"1.0",
    "AdjustmentOpen":"2558.0",
    "AdjustmentHigh":"2598.0",
    "AdjustmentLow":"2558.0",
    "AdjustmentClose":"2560.0",
    "AdjustmentVolume":"3000.0"
  },
  {
    "Date":"2024-12-16T00:00:00.000",
    "Code":"245A",
    "Open":2540.0,
    "High":2572.0,
    "Low":2531.0,
    "Close":2545.0,
    "UpperLimit":"0",
    "LowerLimit":"0",
    "Volume":5200.0,
    "TurnoverValue":"13257200.0",
    "AdjustmentFactor":"1.0",
    "AdjustmentOpen":"2540.0",
    "AdjustmentHigh":"2572.0",
    "AdjustmentLow":"2531.0",
    "AdjustmentClose":"2545.0",
    "AdjustmentVolume":"5200.0"
  },
  {
    "Date":"2024-12-17T00:00:00.000",
    "Code":"245A",
    "Open":2545.0,
    "High":2584.0,
    "Low":2545.0,
    "Close":2565.0,
    "UpperLimit":"0",
    "LowerLimit":"0",
    "Volume":5400.0,
    "TurnoverValue":"13822100.0",
    "AdjustmentFactor":"1.0",
    "AdjustmentOpen":"2545.0",
    "AdjustmentHigh":"2584.0",
    "AdjustmentLow":"2545.0",
    "AdjustmentClose":"2565.0",
    "AdjustmentVolume":"5400.0"
  },
  {
    "Date":"2024-12-18T00:00:00.000",
    "Code":"245A",
    "Open":2582.0,
    "High":2582.0,
    "Low":2552.0,
    "Close":2557.0,
    "UpperLimit":"0",
    "LowerLimit":"0",
    "Volume":3700.0,
    "TurnoverValue":"9486000.0",
    "AdjustmentFactor":"1.0",
    "AdjustmentOpen":"2582.0",
    "AdjustmentHigh":"2582.0",
    "AdjustmentLow":"2552.0",
    "AdjustmentClose":"2557.0",
    "AdjustmentVolume":"3700.0"
  },
  {
    "Date":"2024-12-19T00:00:00.000",
    "Code":"245A",
    "Open":2528.0,
    "High":2550.0,
    "Low":2501.0,
    "Close":2519.0,
    "UpperLimit":"0",
    "LowerLimit":"0",
    "Volume":6500.0,
    "TurnoverValue":"16445300.0",
    "AdjustmentFactor":"1.0",
    "AdjustmentOpen":"2528.0",
    "AdjustmentHigh":"2550.0",
    "AdjustmentLow":"2501.0",
    "AdjustmentClose":"2519.0",
    "AdjustmentVolume":"6500.0"
  },
  {
    "Date":"2024-12-20T00:00:00.000",
    "Code":"245A",
    "Open":2513.0,
    "High":2559.0,
    "Low":2513.0,
    "Close":2554.0,
    "UpperLimit":"0",
    "LowerLimit":"0",
    "Volume":3200.0,
    "TurnoverValue":"8130000.0",
    "AdjustmentFactor":"1.0",
    "AdjustmentOpen":"2513.0",
    "AdjustmentHigh":"2559.0",
    "AdjustmentLow":"2513.0",
    "AdjustmentClose":"2554.0",
    "AdjustmentVolume":"3200.0"
  },
  {
    "Date":"2024-12-23T00:00:00.000",
    "Code":"245A",
    "Open":2554.0,
    "High":2635.0,
    "Low":2554.0,
    "Close":2620.0,
    "UpperLimit":"0",
    "LowerLimit":"0",
    "Volume":9000.0,
    "TurnoverValue":"23426500.0",
    "AdjustmentFactor":"1.0",
    "AdjustmentOpen":"2554.0",
    "AdjustmentHigh":"2635.0",
    "AdjustmentLow":"2554.0",
    "AdjustmentClose":"2620.0",
    "AdjustmentVolume":"9000.0"
  },
  {
    "Date":"2024-12-24T00:00:00.000",
    "Code":"245A",
    "Open":2631.0,
    "High":2631.0,
    "Low":2566.0,
    "Close":2598.0,
    "UpperLimit":"0",
    "LowerLimit":"0",
    "Volume":3900.0,
    "TurnoverValue":"10175500.0",
    "AdjustmentFactor":"1.0",
    "AdjustmentOpen":"2631.0",
    "AdjustmentHigh":"2631.0",
    "AdjustmentLow":"2566.0",
    "AdjustmentClose":"2598.0",
    "AdjustmentVolume":"3900.0"
  },
  {
    "Date":"2024-12-25T00:00:00.000",
    "Code":"245A",
    "Open":2637.0,
    "High":2637.0,
    "Low":2553.0,
    "Close":2600.0,
    "UpperLimit":"0",
    "LowerLimit":"0",
    "Volume":14100.0,
    "TurnoverValue":"36737200.0",
    "AdjustmentFactor":"1.0",
    "AdjustmentOpen":"2637.0",
    "AdjustmentHigh":"2637.0",
    "AdjustmentLow":"2553.0",
    "AdjustmentClose":"2600.0",
    "AdjustmentVolume":"14100.0"
  },
  {
    "Date":"2024-12-26T00:00:00.000",
    "Code":"245A",
    "Open":2605.0,
    "High":2636.0,
    "Low":2600.0,
    "Close":2634.0,
    "UpperLimit":"0",
    "LowerLimit":"0",
    "Volume":7100.0,
    "TurnoverValue":"18536700.0",
    "AdjustmentFactor":"1.0",
    "AdjustmentOpen":"2605.0",
    "AdjustmentHigh":"2636.0",
    "AdjustmentLow":"2600.0",
    "AdjustmentClose":"2634.0",
    "AdjustmentVolume":"7100.0"
  },
  {
    "Date":"2024-12-27T00:00:00.000",
    "Code":"245A",
    "Open":2620.0,
    "High":2633.0,
    "Low":2604.0,
    "Close":2625.0,
    "UpperLimit":"0",
    "LowerLimit":"0",
    "Volume":6100.0,
    "TurnoverValue":"15987200.0",
    "AdjustmentFactor":"1.0",
    "AdjustmentOpen":"2620.0",
    "AdjustmentHigh":"2633.0",
    "AdjustmentLow":"2604.0",
    "AdjustmentClose":"2625.0",
    "AdjustmentVolume":"6100.0"
  },
  {
    "Date":"2024-12-30T00:00:00.000",
    "Code":"245A",
    "Open":2630.0,
    "High":2650.0,
    "Low":2600.0,
    "Close":2650.0,
    "UpperLimit":"0",
    "LowerLimit":"0",
    "Volume":7100.0,
    "TurnoverValue":"18708200.0",
    "AdjustmentFactor":"1.0",
    "AdjustmentOpen":"2630.0",
    "AdjustmentHigh":"2650.0",
    "AdjustmentLow":"2600.0",
    "AdjustmentClose":"2650.0",
    "AdjustmentVolume":"7100.0"
  },
  {
    "Date":"2025-01-06T00:00:00.000",
    "Code":"245A",
    "Open":2660.0,
    "High":2750.0,
    "Low":2655.0,
    "Close":2740.0,
    "UpperLimit":"0",
    "LowerLimit":"0",
    "Volume":24700.0,
    "TurnoverValue":"66823700.0",
    "AdjustmentFactor":"1.0",
    "AdjustmentOpen":"2660.0",
    "AdjustmentHigh":"2750.0",
    "AdjustmentLow":"2655.0",
    "AdjustmentClose":"2740.0",
    "AdjustmentVolume":"24700.0"
  },
  {
    "Date":"2025-01-07T00:00:00.000",
    "Code":"245A",
    "Open":2726.0,
    "High":2748.0,
    "Low":2673.0,
    "Close":2744.0,
    "UpperLimit":"0",
    "LowerLimit":"0",
    "Volume":6500.0,
    "TurnoverValue":"17716400.0",
    "AdjustmentFactor":"1.0",
    "AdjustmentOpen":"2726.0",
    "AdjustmentHigh":"2748.0",
    "AdjustmentLow":"2673.0",
    "AdjustmentClose":"2744.0",
    "AdjustmentVolume":"6500.0"
  },
  {
    "Date":"2025-01-08T00:00:00.000",
    "Code":"245A",
    "Open":2738.0,
    "High":2740.0,
    "Low":2700.0,
    "Close":2712.0,
    "UpperLimit":"0",
    "LowerLimit":"0",
    "Volume":6400.0,
    "TurnoverValue":"17469500.0",
    "AdjustmentFactor":"1.0",
    "AdjustmentOpen":"2738.0",
    "AdjustmentHigh":"2740.0",
    "AdjustmentLow":"2700.0",
    "AdjustmentClose":"2712.0",
    "AdjustmentVolume":"6400.0"
  },
  {
    "Date":"2025-01-09T00:00:00.000",
    "Code":"245A",
    "Open":2730.0,
    "High":2798.0,
    "Low":2672.0,
    "Close":2729.0,
    "UpperLimit":"0",
    "LowerLimit":"0",
    "Volume":21300.0,
    "TurnoverValue":"58427800.0",
    "AdjustmentFactor":"1.0",
    "AdjustmentOpen":"2730.0",
    "AdjustmentHigh":"2798.0",
    "AdjustmentLow":"2672.0",
    "AdjustmentClose":"2729.0",
    "AdjustmentVolume":"21300.0"
  },
  {
    "Date":"2025-01-10T00:00:00.000",
    "Code":"245A",
    "Open":2739.0,
    "High":2740.0,
    "Low":2700.0,
    "Close":2740.0,
    "UpperLimit":"0",
    "LowerLimit":"0",
    "Volume":18200.0,
    "TurnoverValue":"49701900.0",
    "AdjustmentFactor":"1.0",
    "AdjustmentOpen":"2739.0",
    "AdjustmentHigh":"2740.0",
    "AdjustmentLow":"2700.0",
    "AdjustmentClose":"2740.0",
    "AdjustmentVolume":"18200.0"
  },
  {
    "Date":"2025-01-14T00:00:00.000",
    "Code":"245A",
    "Open":2742.0,
    "High":2834.0,
    "Low":2670.0,
    "Close":2707.0,
    "UpperLimit":"0",
    "LowerLimit":"0",
    "Volume":31200.0,
    "TurnoverValue":"85395400.0",
    "AdjustmentFactor":"1.0",
    "AdjustmentOpen":"2742.0",
    "AdjustmentHigh":"2834.0",
    "AdjustmentLow":"2670.0",
    "AdjustmentClose":"2707.0",
    "AdjustmentVolume":"31200.0"
  },
  {
    "Date":"2025-01-15T00:00:00.000",
    "Code":"245A",
    "Open":2557.0,
    "High":2557.0,
    "Low":2207.0,
    "Close":2207.0,
    "UpperLimit":"0",
    "LowerLimit":"1",
    "Volume":117600.0,
    "TurnoverValue":"266804100.0",
    "AdjustmentFactor":"1.0",
    "AdjustmentOpen":"2557.0",
    "AdjustmentHigh":"2557.0",
    "AdjustmentLow":"2207.0",
    "AdjustmentClose":"2207.0",
    "AdjustmentVolume":"117600.0"
  },
  {
    "Date":"2025-01-16T00:00:00.000",
    "Code":"245A",
    "Open":2201.0,
    "High":2233.0,
    "Low":2023.0,
    "Close":2057.0,
    "UpperLimit":"0",
    "LowerLimit":"0",
    "Volume":41000.0,
    "TurnoverValue":"87833000.0",
    "AdjustmentFactor":"1.0",
    "AdjustmentOpen":"2201.0",
    "AdjustmentHigh":"2233.0",
    "AdjustmentLow":"2023.0",
    "AdjustmentClose":"2057.0",
    "AdjustmentVolume":"41000.0"
  },
  {
    "Date":"2025-01-17T00:00:00.000",
    "Code":"245A",
    "Open":2088.0,
    "High":2100.0,
    "Low":2021.0,
    "Close":2085.0,
    "UpperLimit":"0",
    "LowerLimit":"0",
    "Volume":22900.0,
    "TurnoverValue":"47286000.0",
    "AdjustmentFactor":"1.0",
    "AdjustmentOpen":"2088.0",
    "AdjustmentHigh":"2100.0",
    "AdjustmentLow":"2021.0",
    "AdjustmentClose":"2085.0",
    "AdjustmentVolume":"22900.0"
  },
  {
    "Date":"2025-01-20T00:00:00.000",
    "Code":"245A",
    "Open":2087.0,
    "High":2090.0,
    "Low":1986.0,
    "Close":1990.0,
    "UpperLimit":"0",
    "LowerLimit":"0",
    "Volume":24400.0,
    "TurnoverValue":"49196200.0",
    "AdjustmentFactor":"1.0",
    "AdjustmentOpen":"2087.0",
    "AdjustmentHigh":"2090.0",
    "AdjustmentLow":"1986.0",
    "AdjustmentClose":"1990.0",
    "AdjustmentVolume":"24400.0"
  },
  {
    "Date":"2025-01-21T00:00:00.000",
    "Code":"245A",
    "Open":1986.0,
    "High":1986.0,
    "Low":1787.0,
    "Close":1919.0,
    "UpperLimit":"0",
    "LowerLimit":"0",
    "Volume":108800.0,
    "TurnoverValue":"202775600.0",
    "AdjustmentFactor":"1.0",
    "AdjustmentOpen":"1986.0",
    "AdjustmentHigh":"1986.0",
    "AdjustmentLow":"1787.0",
    "AdjustmentClose":"1919.0",
    "AdjustmentVolume":"108800.0"
  },
  {
    "Date":"2025-01-22T00:00:00.000",
    "Code":"245A",
    "Open":1918.0,
    "High":2020.0,
    "Low":1900.0,
    "Close":2020.0,
    "UpperLimit":"0",
    "LowerLimit":"0",
    "Volume":39200.0,
    "TurnoverValue":"77061800.0",
    "AdjustmentFactor":"1.0",
    "AdjustmentOpen":"1918.0",
    "AdjustmentHigh":"2020.0",
    "AdjustmentLow":"1900.0",
    "AdjustmentClose":"2020.0",
    "AdjustmentVolume":"39200.0"
  },
  {
    "Date":"2025-01-23T00:00:00.000",
    "Code":"245A",
    "Open":2019.0,
    "High":2019.0,
    "Low":1949.0,
    "Close":2007.0,
    "UpperLimit":"0",
    "LowerLimit":"0",
    "Volume":11500.0,
    "TurnoverValue":"22968200.0",
    "AdjustmentFactor":"1.0",
    "AdjustmentOpen":"2019.0",
    "AdjustmentHigh":"2019.0",
    "AdjustmentLow":"1949.0",
    "AdjustmentClose":"2007.0",
    "AdjustmentVolume":"11500.0"
  },
  {
    "Date":"2025-01-24T00:00:00.000",
    "Code":"245A",
    "Open":2026.0,
    "High":2113.0,
    "Low":2022.0,
    "Close":2113.0,
    "UpperLimit":"0",
    "LowerLimit":"0",
    "Volume":16400.0,
    "TurnoverValue":"33961500.0",
    "AdjustmentFactor":"1.0",
    "AdjustmentOpen":"2026.0",
    "AdjustmentHigh":"2113.0",
    "AdjustmentLow":"2022.0",
    "AdjustmentClose":"2113.0",
    "AdjustmentVolume":"16400.0"
  },
  {
    "Date":"2025-01-27T00:00:00.000",
    "Code":"245A",
    "Open":2133.0,
    "High":2133.0,
    "Low":2080.0,
    "Close":2124.0,
    "UpperLimit":"0",
    "LowerLimit":"0",
    "Volume":8700.0,
    "TurnoverValue":"18373300.0",
    "AdjustmentFactor":"1.0",
    "AdjustmentOpen":"2133.0",
    "AdjustmentHigh":"2133.0",
    "AdjustmentLow":"2080.0",
    "AdjustmentClose":"2124.0",
    "AdjustmentVolume":"8700.0"
  },
  {
    "Date":"2025-01-28T00:00:00.000",
    "Code":"245A",
    "Open":2132.0,
    "High":2132.0,
    "Low":2093.0,
    "Close":2105.0,
    "UpperLimit":"0",
    "LowerLimit":"0",
    "Volume":5300.0,
    "TurnoverValue":"11234000.0",
    "AdjustmentFactor":"1.0",
    "AdjustmentOpen":"2132.0",
    "AdjustmentHigh":"2132.0",
    "AdjustmentLow":"2093.0",
    "AdjustmentClose":"2105.0",
    "AdjustmentVolume":"5300.0"
  },
  {
    "Date":"2025-01-29T00:00:00.000",
    "Code":"245A",
    "Open":2129.0,
    "High":2131.0,
    "Low":2072.0,
    "Close":2097.0,
    "UpperLimit":"0",
    "LowerLimit":"0",
    "Volume":5300.0,
    "TurnoverValue":"11146800.0",
    "AdjustmentFactor":"1.0",
    "AdjustmentOpen":"2129.0",
    "AdjustmentHigh":"2131.0",
    "AdjustmentLow":"2072.0",
    "AdjustmentClose":"2097.0",
    "AdjustmentVolume":"5300.0"
  },
  {
    "Date":"2025-01-30T00:00:00.000",
    "Code":"245A",
    "Open":2109.0,
    "High":2243.0,
    "Low":2092.0,
    "Close":2208.0,
    "UpperLimit":"0",
    "LowerLimit":"0",
    "Volume":14700.0,
    "TurnoverValue":"31879700.0",
    "AdjustmentFactor":"1.0",
    "AdjustmentOpen":"2109.0",
    "AdjustmentHigh":"2243.0",
    "AdjustmentLow":"2092.0",
    "AdjustmentClose":"2208.0",
    "AdjustmentVolume":"14700.0"
  },
  {
    "Date":"2025-01-31T00:00:00.000",
    "Code":"245A",
    "Open":2207.0,
    "High":2279.0,
    "Low":2172.0,
    "Close":2236.0,
    "UpperLimit":"0",
    "LowerLimit":"0",
    "Volume":9200.0,
    "TurnoverValue":"20450500.0",
    "AdjustmentFactor":"1.0",
    "AdjustmentOpen":"2207.0",
    "AdjustmentHigh":"2279.0",
    "AdjustmentLow":"2172.0",
    "AdjustmentClose":"2236.0",
    "AdjustmentVolume":"9200.0"
  },
  {
    "Date":"2025-02-03T00:00:00.000",
    "Code":"245A",
    "Open":2284.0,
    "High":2284.0,
    "Low":2213.0,
    "Close":2265.0,
    "UpperLimit":"0",
    "LowerLimit":"0",
    "Volume":5800.0,
    "TurnoverValue":"13015100.0",
    "AdjustmentFactor":"1.0",
    "AdjustmentOpen":"2284.0",
    "AdjustmentHigh":"2284.0",
    "AdjustmentLow":"2213.0",
    "AdjustmentClose":"2265.0",
    "AdjustmentVolume":"5800.0"
  },
  {
    "Date":"2025-02-04T00:00:00.000",
    "Code":"245A",
    "Open":2265.0,
    "High":2265.0,
    "Low":2215.0,
    "Close":2225.0,
    "UpperLimit":"0",
    "LowerLimit":"0",
    "Volume":6300.0,
    "TurnoverValue":"14106400.0",
    "AdjustmentFactor":"1.0",
    "AdjustmentOpen":"2265.0",
    "AdjustmentHigh":"2265.0",
    "AdjustmentLow":"2215.0",
    "AdjustmentClose":"2225.0",
    "AdjustmentVolume":"6300.0"
  },
  {
    "Date":"2025-02-05T00:00:00.000",
    "Code":"245A",
    "Open":2225.0,
    "High":2266.0,
    "Low":2216.0,
    "Close":2255.0,
    "UpperLimit":"0",
    "LowerLimit":"0",
    "Volume":2300.0,
    "TurnoverValue":"5146700.0",
    "AdjustmentFactor":"1.0",
    "AdjustmentOpen":"2225.0",
    "AdjustmentHigh":"2266.0",
    "AdjustmentLow":"2216.0",
    "AdjustmentClose":"2255.0",
    "AdjustmentVolume":"2300.0"
  },
  {
    "Date":"2025-02-06T00:00:00.000",
    "Code":"245A",
    "Open":2250.0,
    "High":2250.0,
    "Low":2203.0,
    "Close":2210.0,
    "UpperLimit":"0",
    "LowerLimit":"0",
    "Volume":3400.0,
    "TurnoverValue":"7578700.0",
    "AdjustmentFactor":"1.0",
    "AdjustmentOpen":"2250.0",
    "AdjustmentHigh":"2250.0",
    "AdjustmentLow":"2203.0",
    "AdjustmentClose":"2210.0",
    "AdjustmentVolume":"3400.0"
  },
  {
    "Date":"2025-02-07T00:00:00.000",
    "Code":"245A",
    "Open":2210.0,
    "High":2246.0,
    "Low":2198.0,
    "Close":2216.0,
    "UpperLimit":"0",
    "LowerLimit":"0",
    "Volume":5200.0,
    "TurnoverValue":"11503300.0",
    "AdjustmentFactor":"1.0",
    "AdjustmentOpen":"2210.0",
    "AdjustmentHigh":"2246.0",
    "AdjustmentLow":"2198.0",
    "AdjustmentClose":"2216.0",
    "AdjustmentVolume":"5200.0"
  },
  {
    "Date":"2025-02-10T00:00:00.000",
    "Code":"245A",
    "Open":2216.0,
    "High":2259.0,
    "Low":2216.0,
    "Close":2259.0,
    "UpperLimit":"0",
    "LowerLimit":"0",
    "Volume":3300.0,
    "TurnoverValue":"7396600.0",
    "AdjustmentFactor":"1.0",
    "AdjustmentOpen":"2216.0",
    "AdjustmentHigh":"2259.0",
    "AdjustmentLow":"2216.0",
    "AdjustmentClose":"2259.0",
    "AdjustmentVolume":"3300.0"
  },
  {
    "Date":"2025-02-12T00:00:00.000",
    "Code":"245A",
    "Open":2259.0,
    "High":2299.0,
    "Low":2230.0,
    "Close":2297.0,
    "UpperLimit":"0",
    "LowerLimit":"0",
    "Volume":4200.0,
    "TurnoverValue":"9516900.0",
    "AdjustmentFactor":"1.0",
    "AdjustmentOpen":"2259.0",
    "AdjustmentHigh":"2299.0",
    "AdjustmentLow":"2230.0",
    "AdjustmentClose":"2297.0",
    "AdjustmentVolume":"4200.0"
  },
  {
    "Date":"2025-02-13T00:00:00.000",
    "Code":"245A",
    "Open":2290.0,
    "High":2290.0,
    "Low":2240.0,
    "Close":2254.0,
    "UpperLimit":"0",
    "LowerLimit":"0",
    "Volume":1300.0,
    "TurnoverValue":"2947800.0",
    "AdjustmentFactor":"1.0",
    "AdjustmentOpen":"2290.0",
    "AdjustmentHigh":"2290.0",
    "AdjustmentLow":"2240.0",
    "AdjustmentClose":"2254.0",
    "AdjustmentVolume":"1300.0"
  },
  {
    "Date":"2025-02-14T00:00:00.000",
    "Code":"245A",
    "Open":2254.0,
    "High":2264.0,
    "Low":2231.0,
    "Close":2235.0,
    "UpperLimit":"0",
    "LowerLimit":"0",
    "Volume":2000.0,
    "TurnoverValue":"4495400.0",
    "AdjustmentFactor":"1.0",
    "AdjustmentOpen":"2254.0",
    "AdjustmentHigh":"2264.0",
    "AdjustmentLow":"2231.0",
    "AdjustmentClose":"2235.0",
    "AdjustmentVolume":"2000.0"
  },
  {
    "Date":"2025-02-17T00:00:00.000",
    "Code":"245A",
    "Open":2223.0,
    "High":2252.0,
    "Low":2220.0,
    "Close":2220.0,
    "UpperLimit":"0",
    "LowerLimit":"0",
    "Volume":1800.0,
    "TurnoverValue":"4027400.0",
    "AdjustmentFactor":"1.0",
    "AdjustmentOpen":"2223.0",
    "AdjustmentHigh":"2252.0",
    "AdjustmentLow":"2220.0",
    "AdjustmentClose":"2220.0",
    "AdjustmentVolume":"1800.0"
  },
  {
    "Date":"2025-02-18T00:00:00.000",
    "Code":"245A",
    "Open":2220.0,
    "High":2246.0,
    "Low":2220.0,
    "Close":2246.0,
    "UpperLimit":"0",
    "LowerLimit":"0",
    "Volume":2000.0,
    "TurnoverValue":"4467100.0",
    "AdjustmentFactor":"1.0",
    "AdjustmentOpen":"2220.0",
    "AdjustmentHigh":"2246.0",
    "AdjustmentLow":"2220.0",
    "AdjustmentClose":"2246.0",
    "AdjustmentVolume":"2000.0"
  },
  {
    "Date":"2025-02-19T00:00:00.000",
    "Code":"245A",
    "Open":2248.0,
    "High":2255.0,
    "Low":2223.0,
    "Close":2235.0,
    "UpperLimit":"0",
    "LowerLimit":"0",
    "Volume":2500.0,
    "TurnoverValue":"5606800.0",
    "AdjustmentFactor":"1.0",
    "AdjustmentOpen":"2248.0",
    "AdjustmentHigh":"2255.0",
    "AdjustmentLow":"2223.0",
    "AdjustmentClose":"2235.0",
    "AdjustmentVolume":"2500.0"
  },
  {
    "Date":"2025-02-20T00:00:00.000",
    "Code":"245A",
    "Open":2226.0,
    "High":2234.0,
    "Low":2205.0,
    "Close":2234.0,
    "UpperLimit":"0",
    "LowerLimit":"0",
    "Volume":3400.0,
    "TurnoverValue":"7547500.0",
    "AdjustmentFactor":"1.0",
    "AdjustmentOpen":"2226.0",
    "AdjustmentHigh":"2234.0",
    "AdjustmentLow":"2205.0",
    "AdjustmentClose":"2234.0",
    "AdjustmentVolume":"3400.0"
  },
  {
    "Date":"2025-02-21T00:00:00.000",
    "Code":"245A",
    "Open":2209.0,
    "High":2221.0,
    "Low":2201.0,
    "Close":2217.0,
    "UpperLimit":"0",
    "LowerLimit":"0",
    "Volume":2900.0,
    "TurnoverValue":"6403500.0",
    "AdjustmentFactor":"1.0",
    "AdjustmentOpen":"2209.0",
    "AdjustmentHigh":"2221.0",
    "AdjustmentLow":"2201.0",
    "AdjustmentClose":"2217.0",
    "AdjustmentVolume":"2900.0"
  },
  {
    "Date":"2025-02-25T00:00:00.000",
    "Code":"245A",
    "Open":2203.0,
    "High":2208.0,
    "Low":2178.0,
    "Close":2194.0,
    "UpperLimit":"0",
    "LowerLimit":"0",
    "Volume":5200.0,
    "TurnoverValue":"11399000.0",
    "AdjustmentFactor":"1.0",
    "AdjustmentOpen":"2203.0",
    "AdjustmentHigh":"2208.0",
    "AdjustmentLow":"2178.0",
    "AdjustmentClose":"2194.0",
    "AdjustmentVolume":"5200.0"
  },
  {
    "Date":"2025-02-26T00:00:00.000",
    "Code":"245A",
    "Open":2173.0,
    "High":2203.0,
    "Low":2161.0,
    "Close":2185.0,
    "UpperLimit":"0",
    "LowerLimit":"0",
    "Volume":8900.0,
    "TurnoverValue":"19377000.0",
    "AdjustmentFactor":"1.0",
    "AdjustmentOpen":"2173.0",
    "AdjustmentHigh":"2203.0",
    "AdjustmentLow":"2161.0",
    "AdjustmentClose":"2185.0",
    "AdjustmentVolume":"8900.0"
  },
  {
    "Date":"2025-02-27T00:00:00.000",
    "Code":"245A",
    "Open":2135.0,
    "High":2159.0,
    "Low":2116.0,
    "Close":2141.0,
    "UpperLimit":"0",
    "LowerLimit":"0",
    "Volume":2700.0,
    "TurnoverValue":"5771000.0",
    "AdjustmentFactor":"1.0",
    "AdjustmentOpen":"2135.0",
    "AdjustmentHigh":"2159.0",
    "AdjustmentLow":"2116.0",
    "AdjustmentClose":"2141.0",
    "AdjustmentVolume":"2700.0"
  },
  {
    "Date":"2025-02-28T00:00:00.000",
    "Code":"245A",
    "Open":2137.0,
    "High":2149.0,
    "Low":2067.0,
    "Close":2083.0,
    "UpperLimit":"0",
    "LowerLimit":"0",
    "Volume":5100.0,
    "TurnoverValue":"10727400.0",
    "AdjustmentFactor":"1.0",
    "AdjustmentOpen":"2137.0",
    "AdjustmentHigh":"2149.0",
    "AdjustmentLow":"2067.0",
    "AdjustmentClose":"2083.0",
    "AdjustmentVolume":"5100.0"
  },
  {
    "Date":"2025-03-03T00:00:00.000",
    "Code":"245A",
    "Open":2097.0,
    "High":2120.0,
    "Low":2087.0,
    "Close":2104.0,
    "UpperLimit":"0",
    "LowerLimit":"0",
    "Volume":1300.0,
    "TurnoverValue":"2736200.0",
    "AdjustmentFactor":"1.0",
    "AdjustmentOpen":"2097.0",
    "AdjustmentHigh":"2120.0",
    "AdjustmentLow":"2087.0",
    "AdjustmentClose":"2104.0",
    "AdjustmentVolume":"1300.0"
  },
  {
    "Date":"2025-03-04T00:00:00.000",
    "Code":"245A",
    "Open":2104.0,
    "High":2107.0,
    "Low":2088.0,
    "Close":2107.0,
    "UpperLimit":"0",
    "LowerLimit":"0",
    "Volume":7300.0,
    "TurnoverValue":"15340300.0",
    "AdjustmentFactor":"1.0",
    "AdjustmentOpen":"2104.0",
    "AdjustmentHigh":"2107.0",
    "AdjustmentLow":"2088.0",
    "AdjustmentClose":"2107.0",
    "AdjustmentVolume":"7300.0"
  },
  {
    "Date":"2025-03-05T00:00:00.000",
    "Code":"245A",
    "Open":2103.0,
    "High":2103.0,
    "Low":2100.0,
    "Close":2100.0,
    "UpperLimit":"0",
    "LowerLimit":"0",
    "Volume":1000.0,
    "TurnoverValue":"2102400.0",
    "AdjustmentFactor":"1.0",
    "AdjustmentOpen":"2103.0",
    "AdjustmentHigh":"2103.0",
    "AdjustmentLow":"2100.0",
    "AdjustmentClose":"2100.0",
    "AdjustmentVolume":"1000.0"
  },
  {
    "Date":"2025-03-06T00:00:00.000",
    "Code":"245A",
    "Open":2150.0,
    "High":2150.0,
    "Low":2118.0,
    "Close":2119.0,
    "UpperLimit":"0",
    "LowerLimit":"0",
    "Volume":1000.0,
    "TurnoverValue":"2132500.0",
    "AdjustmentFactor":"1.0",
    "AdjustmentOpen":"2150.0",
    "AdjustmentHigh":"2150.0",
    "AdjustmentLow":"2118.0",
    "AdjustmentClose":"2119.0",
    "AdjustmentVolume":"1000.0"
  },
  {
    "Date":"2025-03-07T00:00:00.000",
    "Code":"245A",
    "Open":2118.0,
    "High":2119.0,
    "Low":2015.0,
    "Close":2020.0,
    "UpperLimit":"0",
    "LowerLimit":"0",
    "Volume":7700.0,
    "TurnoverValue":"15975900.0",
    "AdjustmentFactor":"1.0",
    "AdjustmentOpen":"2118.0",
    "AdjustmentHigh":"2119.0",
    "AdjustmentLow":"2015.0",
    "AdjustmentClose":"2020.0",
    "AdjustmentVolume":"7700.0"
  },
  {
    "Date":"2025-03-10T00:00:00.000",
    "Code":"245A",
    "Open":2120.0,
    "High":2120.0,
    "Low":2050.0,
    "Close":2101.0,
    "UpperLimit":"0",
    "LowerLimit":"0",
    "Volume":4300.0,
    "TurnoverValue":"9068100.0",
    "AdjustmentFactor":"1.0",
    "AdjustmentOpen":"2120.0",
    "AdjustmentHigh":"2120.0",
    "AdjustmentLow":"2050.0",
    "AdjustmentClose":"2101.0",
    "AdjustmentVolume":"4300.0"
  },
  {
    "Date":"2025-03-11T00:00:00.000",
    "Code":"245A",
    "Open":2101.0,
    "High":2146.0,
    "Low":2101.0,
    "Close":2136.0,
    "UpperLimit":"0",
    "LowerLimit":"0",
    "Volume":3300.0,
    "TurnoverValue":"6969900.0",
    "AdjustmentFactor":"1.0",
    "AdjustmentOpen":"2101.0",
    "AdjustmentHigh":"2146.0",
    "AdjustmentLow":"2101.0",
    "AdjustmentClose":"2136.0",
    "AdjustmentVolume":"3300.0"
  },
  {
    "Date":"2025-03-12T00:00:00.000",
    "Code":"245A",
    "Open":2136.0,
    "High":2178.0,
    "Low":2135.0,
    "Close":2145.0,
    "UpperLimit":"0",
    "LowerLimit":"0",
    "Volume":1700.0,
    "TurnoverValue":"3645200.0",
    "AdjustmentFactor":"1.0",
    "AdjustmentOpen":"2136.0",
    "AdjustmentHigh":"2178.0",
    "AdjustmentLow":"2135.0",
    "AdjustmentClose":"2145.0",
    "AdjustmentVolume":"1700.0"
  },
  {
    "Date":"2025-03-13T00:00:00.000",
    "Code":"245A",
    "Open":2108.0,
    "High":2111.0,
    "Low":2108.0,
    "Close":2111.0,
    "UpperLimit":"0",
    "LowerLimit":"0",
    "Volume":800.0,
    "TurnoverValue":"1687600.0",
    "AdjustmentFactor":"1.0",
    "AdjustmentOpen":"2108.0",
    "AdjustmentHigh":"2111.0",
    "AdjustmentLow":"2108.0",
    "AdjustmentClose":"2111.0",
    "AdjustmentVolume":"800.0"
  },
  {
    "Date":"2025-03-14T00:00:00.000",
    "Code":"245A",
    "Open":2153.0,
    "High":2162.0,
    "Low":2112.0,
    "Close":2145.0,
    "UpperLimit":"0",
    "LowerLimit":"0",
    "Volume":1200.0,
    "TurnoverValue":"2575900.0",
    "AdjustmentFactor":"1.0",
    "AdjustmentOpen":"2153.0",
    "AdjustmentHigh":"2162.0",
    "AdjustmentLow":"2112.0",
    "AdjustmentClose":"2145.0",
    "AdjustmentVolume":"1200.0"
  },
  {
    "Date":"2025-03-17T00:00:00.000",
    "Code":"245A",
    "Open":2174.0,
    "High":2193.0,
    "Low":2163.0,
    "Close":2169.0,
    "UpperLimit":"0",
    "LowerLimit":"0",
    "Volume":1600.0,
    "TurnoverValue":"3480300.0",
    "AdjustmentFactor":"1.0",
    "AdjustmentOpen":"2174.0",
    "AdjustmentHigh":"2193.0",
    "AdjustmentLow":"2163.0",
    "AdjustmentClose":"2169.0",
    "AdjustmentVolume":"1600.0"
  },
  {
    "Date":"2025-03-18T00:00:00.000",
    "Code":"245A",
    "Open":2181.0,
    "High":2181.0,
    "Low":2106.0,
    "Close":2106.0,
    "UpperLimit":"0",
    "LowerLimit":"0",
    "Volume":4500.0,
    "TurnoverValue":"9524100.0",
    "AdjustmentFactor":"1.0",
    "AdjustmentOpen":"2181.0",
    "AdjustmentHigh":"2181.0",
    "AdjustmentLow":"2106.0",
    "AdjustmentClose":"2106.0",
    "AdjustmentVolume":"4500.0"
  },
  {
    "Date":"2025-03-19T00:00:00.000",
    "Code":"245A",
    "Open":2106.0,
    "High":2152.0,
    "Low":2106.0,
    "Close":2122.0,
    "UpperLimit":"0",
    "LowerLimit":"0",
    "Volume":1000.0,
    "TurnoverValue":"2126200.0",
    "AdjustmentFactor":"1.0",
    "AdjustmentOpen":"2106.0",
    "AdjustmentHigh":"2152.0",
    "AdjustmentLow":"2106.0",
    "AdjustmentClose":"2122.0",
    "AdjustmentVolume":"1000.0"
  },
  {
    "Date":"2025-03-21T00:00:00.000",
    "Code":"245A",
    "Open":2122.0,
    "High":2150.0,
    "Low":2112.0,
    "Close":2148.0,
    "UpperLimit":"0",
    "LowerLimit":"0",
    "Volume":3200.0,
    "TurnoverValue":"6823000.0",
    "AdjustmentFactor":"1.0",
    "AdjustmentOpen":"2122.0",
    "AdjustmentHigh":"2150.0",
    "AdjustmentLow":"2112.0",
    "AdjustmentClose":"2148.0",
    "AdjustmentVolume":"3200.0"
  },
  {
    "Date":"2025-03-24T00:00:00.000",
    "Code":"245A",
    "Open":2159.0,
    "High":2194.0,
    "Low":2144.0,
    "Close":2193.0,
    "UpperLimit":"0",
    "LowerLimit":"0",
    "Volume":2200.0,
    "TurnoverValue":"4785000.0",
    "AdjustmentFactor":"1.0",
    "AdjustmentOpen":"2159.0",
    "AdjustmentHigh":"2194.0",
    "AdjustmentLow":"2144.0",
    "AdjustmentClose":"2193.0",
    "AdjustmentVolume":"2200.0"
  },
  {
    "Date":"2025-03-25T00:00:00.000",
    "Code":"245A",
    "Open":2226.0,
    "High":2248.0,
    "Low":2161.0,
    "Close":2190.0,
    "UpperLimit":"0",
    "LowerLimit":"0",
    "Volume":2600.0,
    "TurnoverValue":"5733700.0",
    "AdjustmentFactor":"1.0",
    "AdjustmentOpen":"2226.0",
    "AdjustmentHigh":"2248.0",
    "AdjustmentLow":"2161.0",
    "AdjustmentClose":"2190.0",
    "AdjustmentVolume":"2600.0"
  },
  {
    "Date":"2025-03-26T00:00:00.000",
    "Code":"245A",
    "Open":2160.0,
    "High":2180.0,
    "Low":2138.0,
    "Close":2138.0,
    "UpperLimit":"0",
    "LowerLimit":"0",
    "Volume":9500.0,
    "TurnoverValue":"20497900.0",
    "AdjustmentFactor":"1.0",
    "AdjustmentOpen":"2160.0",
    "AdjustmentHigh":"2180.0",
    "AdjustmentLow":"2138.0",
    "AdjustmentClose":"2138.0",
    "AdjustmentVolume":"9500.0"
  },
  {
    "Date":"2025-03-27T00:00:00.000",
    "Code":"245A",
    "Open":2124.0,
    "High":2146.0,
    "Low":2116.0,
    "Close":2116.0,
    "UpperLimit":"0",
    "LowerLimit":"0",
    "Volume":1500.0,
    "TurnoverValue":"3193300.0",
    "AdjustmentFactor":"1.0",
    "AdjustmentOpen":"2124.0",
    "AdjustmentHigh":"2146.0",
    "AdjustmentLow":"2116.0",
    "AdjustmentClose":"2116.0",
    "AdjustmentVolume":"1500.0"
  },
  {
    "Date":"2025-03-28T00:00:00.000",
    "Code":"245A",
    "Open":2111.0,
    "High":2146.0,
    "Low":2105.0,
    "Close":2121.0,
    "UpperLimit":"0",
    "LowerLimit":"0",
    "Volume":1500.0,
    "TurnoverValue":"3175600.0",
    "AdjustmentFactor":"1.0",
    "AdjustmentOpen":"2111.0",
    "AdjustmentHigh":"2146.0",
    "AdjustmentLow":"2105.0",
    "AdjustmentClose":"2121.0",
    "AdjustmentVolume":"1500.0"
  },
  {
    "Date":"2025-03-31T00:00:00.000",
    "Code":"245A",
    "Open":2111.0,
    "High":2182.0,
    "Low":2110.0,
    "Close":2182.0,
    "UpperLimit":"0",
    "LowerLimit":"0",
    "Volume":2300.0,
    "TurnoverValue":"4920600.0",
    "AdjustmentFactor":"1.0",
    "AdjustmentOpen":"2111.0",
    "AdjustmentHigh":"2182.0",
    "AdjustmentLow":"2110.0",
    "AdjustmentClose":"2182.0",
    "AdjustmentVolume":"2300.0"
  },
  {
    "Date":"2025-04-01T00:00:00.000",
    "Code":"245A",
    "Open":2178.0,
    "High":2178.0,
    "Low":2107.0,
    "Close":2122.0,
    "UpperLimit":"0",
    "LowerLimit":"0",
    "Volume":3300.0,
    "TurnoverValue":"7023600.0",
    "AdjustmentFactor":"1.0",
    "AdjustmentOpen":"2178.0",
    "AdjustmentHigh":"2178.0",
    "AdjustmentLow":"2107.0",
    "AdjustmentClose":"2122.0",
    "AdjustmentVolume":"3300.0"
  },
  {
    "Date":"2025-04-02T00:00:00.000",
    "Code":"245A",
    "Open":2165.0,
    "High":2189.0,
    "Low":2123.0,
    "Close":2153.0,
    "UpperLimit":"0",
    "LowerLimit":"0",
    "Volume":3700.0,
    "TurnoverValue":"8014000.0",
    "AdjustmentFactor":"1.0",
    "AdjustmentOpen":"2165.0",
    "AdjustmentHigh":"2189.0",
    "AdjustmentLow":"2123.0",
    "AdjustmentClose":"2153.0",
    "AdjustmentVolume":"3700.0"
  },
  {
    "Date":"2025-04-03T00:00:00.000",
    "Code":"245A",
    "Open":2141.0,
    "High":2207.0,
    "Low":2115.0,
    "Close":2189.0,
    "UpperLimit":"0",
    "LowerLimit":"0",
    "Volume":4300.0,
    "TurnoverValue":"9242000.0",
    "AdjustmentFactor":"1.0",
    "AdjustmentOpen":"2141.0",
    "AdjustmentHigh":"2207.0",
    "AdjustmentLow":"2115.0",
    "AdjustmentClose":"2189.0",
    "AdjustmentVolume":"4300.0"
  },
  {
    "Date":"2025-04-04T00:00:00.000",
    "Code":"245A",
    "Open":2114.0,
    "High":2138.0,
    "Low":1988.0,
    "Close":2038.0,
    "UpperLimit":"0",
    "LowerLimit":"0",
    "Volume":21500.0,
    "TurnoverValue":"43689500.0",
    "AdjustmentFactor":"1.0",
    "AdjustmentOpen":"2114.0",
    "AdjustmentHigh":"2138.0",
    "AdjustmentLow":"1988.0",
    "AdjustmentClose":"2038.0",
    "AdjustmentVolume":"21500.0"
  },
  {
    "Date":"2025-04-07T00:00:00.000",
    "Code":"245A",
    "Open":2002.0,
    "High":2020.0,
    "Low":1839.0,
    "Close":1839.0,
    "UpperLimit":"0",
    "LowerLimit":"0",
    "Volume":33400.0,
    "TurnoverValue":"65246100.0",
    "AdjustmentFactor":"1.0",
    "AdjustmentOpen":"2002.0",
    "AdjustmentHigh":"2020.0",
    "AdjustmentLow":"1839.0",
    "AdjustmentClose":"1839.0",
    "AdjustmentVolume":"33400.0"
  },
  {
    "Date":"2025-04-08T00:00:00.000",
    "Code":"245A",
    "Open":1978.0,
    "High":2019.0,
    "Low":1896.0,
    "Close":1941.0,
    "UpperLimit":"0",
    "LowerLimit":"0",
    "Volume":13600.0,
    "TurnoverValue":"26807200.0",
    "AdjustmentFactor":"1.0",
    "AdjustmentOpen":"1978.0",
    "AdjustmentHigh":"2019.0",
    "AdjustmentLow":"1896.0",
    "AdjustmentClose":"1941.0",
    "AdjustmentVolume":"13600.0"
  },
  {
    "Date":"2025-04-09T00:00:00.000",
    "Code":"245A",
    "Open":1981.0,
    "High":2000.0,
    "Low":1887.0,
    "Close":1983.0,
    "UpperLimit":"0",
    "LowerLimit":"0",
    "Volume":6800.0,
    "TurnoverValue":"13421000.0",
    "AdjustmentFactor":"1.0",
    "AdjustmentOpen":"1981.0",
    "AdjustmentHigh":"2000.0",
    "AdjustmentLow":"1887.0",
    "AdjustmentClose":"1983.0",
    "AdjustmentVolume":"6800.0"
  },
  {
    "Date":"2025-04-10T00:00:00.000",
    "Code":"245A",
    "Open":2078.0,
    "High":2078.0,
    "Low":2002.0,
    "Close":2002.0,
    "UpperLimit":"0",
    "LowerLimit":"0",
    "Volume":3400.0,
    "TurnoverValue":"6901400.0",
    "AdjustmentFactor":"1.0",
    "AdjustmentOpen":"2078.0",
    "AdjustmentHigh":"2078.0",
    "AdjustmentLow":"2002.0",
    "AdjustmentClose":"2002.0",
    "AdjustmentVolume":"3400.0"
  },
  {
    "Date":"2025-04-11T00:00:00.000",
    "Code":"245A",
    "Open":1976.0,
    "High":2062.0,
    "Low":1918.0,
    "Close":1985.0,
    "UpperLimit":"0",
    "LowerLimit":"0",
    "Volume":3200.0,
    "TurnoverValue":"6278700.0",
    "AdjustmentFactor":"1.0",
    "AdjustmentOpen":"1976.0",
    "AdjustmentHigh":"2062.0",
    "AdjustmentLow":"1918.0",
    "AdjustmentClose":"1985.0",
    "AdjustmentVolume":"3200.0"
  },
  {
    "Date":"2025-04-14T00:00:00.000",
    "Code":"245A",
    "Open":2000.0,
    "High":2044.0,
    "Low":1920.0,
    "Close":1999.0,
    "UpperLimit":"0",
    "LowerLimit":"0",
    "Volume":19200.0,
    "TurnoverValue":"37976000.0",
    "AdjustmentFactor":"1.0",
    "AdjustmentOpen":"2000.0",
    "AdjustmentHigh":"2044.0",
    "AdjustmentLow":"1920.0",
    "AdjustmentClose":"1999.0",
    "AdjustmentVolume":"19200.0"
  },
  {
    "Date":"2025-04-15T00:00:00.000",
    "Code":"245A",
    "Open":1923.0,
    "High":2004.0,
    "Low":1920.0,
    "Close":1952.0,
    "UpperLimit":"0",
    "LowerLimit":"0",
    "Volume":11600.0,
    "TurnoverValue":"22651900.0",
    "AdjustmentFactor":"1.0",
    "AdjustmentOpen":"1923.0",
    "AdjustmentHigh":"2004.0",
    "AdjustmentLow":"1920.0",
    "AdjustmentClose":"1952.0",
    "AdjustmentVolume":"11600.0"
  },
  {
    "Date":"2025-04-16T00:00:00.000",
    "Code":"245A",
    "Open":1960.0,
    "High":2047.0,
    "Low":1960.0,
    "Close":1980.0,
    "UpperLimit":"0",
    "LowerLimit":"0",
    "Volume":5100.0,
    "TurnoverValue":"10112400.0",
    "AdjustmentFactor":"1.0",
    "AdjustmentOpen":"1960.0",
    "AdjustmentHigh":"2047.0",
    "AdjustmentLow":"1960.0",
    "AdjustmentClose":"1980.0",
    "AdjustmentVolume":"5100.0"
  },
  {
    "Date":"2025-04-17T00:00:00.000",
    "Code":"245A",
    "Open":1983.0,
    "High":1983.0,
    "Low":1956.0,
    "Close":1962.0,
    "UpperLimit":"0",
    "LowerLimit":"0",
    "Volume":500.0,
    "TurnoverValue":"982500.0",
    "AdjustmentFactor":"1.0",
    "AdjustmentOpen":"1983.0",
    "AdjustmentHigh":"1983.0",
    "AdjustmentLow":"1956.0",
    "AdjustmentClose":"1962.0",
    "AdjustmentVolume":"500.0"
  },
  {
    "Date":"2025-04-18T00:00:00.000",
    "Code":"245A",
    "Open":2002.0,
    "High":2032.0,
    "Low":1994.0,
    "Close":2032.0,
    "UpperLimit":"0",
    "LowerLimit":"0",
    "Volume":1500.0,
    "TurnoverValue":"3014400.0",
    "AdjustmentFactor":"1.0",
    "AdjustmentOpen":"2002.0",
    "AdjustmentHigh":"2032.0",
    "AdjustmentLow":"1994.0",
    "AdjustmentClose":"2032.0",
    "AdjustmentVolume":"1500.0"
  },
  {
    "Date":"2025-04-21T00:00:00.000",
    "Code":"245A",
    "Open":2035.0,
    "High":2252.0,
    "Low":2035.0,
    "Close":2250.0,
    "UpperLimit":"0",
    "LowerLimit":"0",
    "Volume":21700.0,
    "TurnoverValue":"47768300.0",
    "AdjustmentFactor":"1.0",
    "AdjustmentOpen":"2035.0",
    "AdjustmentHigh":"2252.0",
    "AdjustmentLow":"2035.0",
    "AdjustmentClose":"2250.0",
    "AdjustmentVolume":"21700.0"
  },
  {
    "Date":"2025-04-22T00:00:00.000",
    "Code":"245A",
    "Open":2250.0,
    "High":2279.0,
    "Low":2210.0,
    "Close":2260.0,
    "UpperLimit":"0",
    "LowerLimit":"0",
    "Volume":5700.0,
    "TurnoverValue":"12813700.0",
    "AdjustmentFactor":"1.0",
    "AdjustmentOpen":"2250.0",
    "AdjustmentHigh":"2279.0",
    "AdjustmentLow":"2210.0",
    "AdjustmentClose":"2260.0",
    "AdjustmentVolume":"5700.0"
  },
  {
    "Date":"2025-04-23T00:00:00.000",
    "Code":"245A",
    "Open":2236.0,
    "High":2274.0,
    "Low":2201.0,
    "Close":2274.0,
    "UpperLimit":"0",
    "LowerLimit":"0",
    "Volume":3500.0,
    "TurnoverValue":"7857600.0",
    "AdjustmentFactor":"1.0",
    "AdjustmentOpen":"2236.0",
    "AdjustmentHigh":"2274.0",
    "AdjustmentLow":"2201.0",
    "AdjustmentClose":"2274.0",
    "AdjustmentVolume":"3500.0"
  },
  {
    "Date":"2025-04-24T00:00:00.000",
    "Code":"245A",
    "Open":2280.0,
    "High":2433.0,
    "Low":2171.0,
    "Close":2430.0,
    "UpperLimit":"0",
    "LowerLimit":"0",
    "Volume":17600.0,
    "TurnoverValue":"41008500.0",
    "AdjustmentFactor":"1.0",
    "AdjustmentOpen":"2280.0",
    "AdjustmentHigh":"2433.0",
    "AdjustmentLow":"2171.0",
    "AdjustmentClose":"2430.0",
    "AdjustmentVolume":"17600.0"
  },
  {
    "Date":"2025-04-25T00:00:00.000",
    "Code":"245A",
    "Open":2427.0,
    "High":2427.0,
    "Low":2247.0,
    "Close":2373.0,
    "UpperLimit":"0",
    "LowerLimit":"0",
    "Volume":5300.0,
    "TurnoverValue":"12342200.0",
    "AdjustmentFactor":"1.0",
    "AdjustmentOpen":"2427.0",
    "AdjustmentHigh":"2427.0",
    "AdjustmentLow":"2247.0",
    "AdjustmentClose":"2373.0",
    "AdjustmentVolume":"5300.0"
  },
  {
    "Date":"2025-04-28T00:00:00.000",
    "Code":"245A",
    "Open":2408.0,
    "High":2410.0,
    "Low":2289.0,
    "Close":2388.0,
    "UpperLimit":"0",
    "LowerLimit":"0",
    "Volume":3100.0,
    "TurnoverValue":"7356100.0",
    "AdjustmentFactor":"1.0",
    "AdjustmentOpen":"2408.0",
    "AdjustmentHigh":"2410.0",
    "AdjustmentLow":"2289.0",
    "AdjustmentClose":"2388.0",
    "AdjustmentVolume":"3100.0"
  },
  {
    "Date":"2025-04-30T00:00:00.000",
    "Code":"245A",
    "Open":2388.0,
    "High":2440.0,
    "Low":2329.0,
    "Close":2329.0,
    "UpperLimit":"0",
    "LowerLimit":"0",
    "Volume":2400.0,
    "TurnoverValue":"5673000.0",
    "AdjustmentFactor":"1.0",
    "AdjustmentOpen":"2388.0",
    "AdjustmentHigh":"2440.0",
    "AdjustmentLow":"2329.0",
    "AdjustmentClose":"2329.0",
    "AdjustmentVolume":"2400.0"
  },
  {
    "Date":"2025-05-01T00:00:00.000",
    "Code":"245A",
    "Open":2379.0,
    "High":2379.0,
    "Low":2326.0,
    "Close":2326.0,
    "UpperLimit":"0",
    "LowerLimit":"0",
    "Volume":500.0,
    "TurnoverValue":"1180200.0",
    "AdjustmentFactor":"1.0",
    "AdjustmentOpen":"2379.0",
    "AdjustmentHigh":"2379.0",
    "AdjustmentLow":"2326.0",
    "AdjustmentClose":"2326.0",
    "AdjustmentVolume":"500.0"
  },
  {
    "Date":"2025-05-02T00:00:00.000",
    "Code":"245A",
    "Open":2326.0,
    "High":2326.0,
    "Low":2238.0,
    "Close":2238.0,
    "UpperLimit":"0",
    "LowerLimit":"0",
    "Volume":2700.0,
    "TurnoverValue":"6140100.0",
    "AdjustmentFactor":"1.0",
    "AdjustmentOpen":"2326.0",
    "AdjustmentHigh":"2326.0",
    "AdjustmentLow":"2238.0",
    "AdjustmentClose":"2238.0",
    "AdjustmentVolume":"2700.0"
  },
  {
    "Date":"2025-05-07T00:00:00.000",
    "Code":"245A",
    "Open":2283.0,
    "High":2285.0,
    "Low":2239.0,
    "Close":2239.0,
    "UpperLimit":"0",
    "LowerLimit":"0",
    "Volume":1100.0,
    "TurnoverValue":"2497900.0",
    "AdjustmentFactor":"1.0",
    "AdjustmentOpen":"2283.0",
    "AdjustmentHigh":"2285.0",
    "AdjustmentLow":"2239.0",
    "AdjustmentClose":"2239.0",
    "AdjustmentVolume":"1100.0"
  },
  {
    "Date":"2025-05-08T00:00:00.000",
    "Code":"245A",
    "Open":2232.0,
    "High":2296.0,
    "Low":2232.0,
    "Close":2296.0,
    "UpperLimit":"0",
    "LowerLimit":"0",
    "Volume":700.0,
    "TurnoverValue":"1586700.0",
    "AdjustmentFactor":"1.0",
    "AdjustmentOpen":"2232.0",
    "AdjustmentHigh":"2296.0",
    "AdjustmentLow":"2232.0",
    "AdjustmentClose":"2296.0",
    "AdjustmentVolume":"700.0"
  },
  {
    "Date":"2025-05-09T00:00:00.000",
    "Code":"245A",
    "Open":2246.0,
    "High":2295.0,
    "Low":2234.0,
    "Close":2286.0,
    "UpperLimit":"0",
    "LowerLimit":"0",
    "Volume":600.0,
    "TurnoverValue":"1358700.0",
    "AdjustmentFactor":"1.0",
    "AdjustmentOpen":"2246.0",
    "AdjustmentHigh":"2295.0",
    "AdjustmentLow":"2234.0",
    "AdjustmentClose":"2286.0",
    "AdjustmentVolume":"600.0"
  },
  {
    "Date":"2025-05-12T00:00:00.000",
    "Code":"245A",
    "Open":2395.0,
    "High":2500.0,
    "Low":2355.0,
    "Close":2500.0,
    "UpperLimit":"0",
    "LowerLimit":"0",
    "Volume":8100.0,
    "TurnoverValue":"19757400.0",
    "AdjustmentFactor":"1.0",
    "AdjustmentOpen":"2395.0",
    "AdjustmentHigh":"2500.0",
    "AdjustmentLow":"2355.0",
    "AdjustmentClose":"2500.0",
    "AdjustmentVolume":"8100.0"
  },
  {
    "Date":"2025-05-13T00:00:00.000",
    "Code":"245A",
    "Open":2589.0,
    "High":2619.0,
    "Low":2502.0,
    "Close":2502.0,
    "UpperLimit":"0",
    "LowerLimit":"0",
    "Volume":6800.0,
    "TurnoverValue":"17332800.0",
    "AdjustmentFactor":"1.0",
    "AdjustmentOpen":"2589.0",
    "AdjustmentHigh":"2619.0",
    "AdjustmentLow":"2502.0",
    "AdjustmentClose":"2502.0",
    "AdjustmentVolume":"6800.0"
  },
  {
    "Date":"2025-05-14T00:00:00.000",
    "Code":"245A",
    "Open":2510.0,
    "High":2566.0,
    "Low":2442.0,
    "Close":2442.0,
    "UpperLimit":"0",
    "LowerLimit":"0",
    "Volume":1700.0,
    "TurnoverValue":"4269000.0",
    "AdjustmentFactor":"1.0",
    "AdjustmentOpen":"2510.0",
    "AdjustmentHigh":"2566.0",
    "AdjustmentLow":"2442.0",
    "AdjustmentClose":"2442.0",
    "AdjustmentVolume":"1700.0"
  },
  {
    "Date":"2025-05-15T00:00:00.000",
    "Code":"245A",
    "Open":2392.0,
    "High":2497.0,
    "Low":2391.0,
    "Close":2497.0,
    "UpperLimit":"0",
    "LowerLimit":"0",
    "Volume":2300.0,
    "TurnoverValue":"5600800.0",
    "AdjustmentFactor":"1.0",
    "AdjustmentOpen":"2392.0",
    "AdjustmentHigh":"2497.0",
    "AdjustmentLow":"2391.0",
    "AdjustmentClose":"2497.0",
    "AdjustmentVolume":"2300.0"
  },
  {
    "Date":"2025-05-16T00:00:00.000",
    "Code":"245A",
    "Open":2447.0,
    "High":2499.0,
    "Low":2428.0,
    "Close":2499.0,
    "UpperLimit":"0",
    "LowerLimit":"0",
    "Volume":1000.0,
    "TurnoverValue":"2472200.0",
    "AdjustmentFactor":"1.0",
    "AdjustmentOpen":"2447.0",
    "AdjustmentHigh":"2499.0",
    "AdjustmentLow":"2428.0",
    "AdjustmentClose":"2499.0",
    "AdjustmentVolume":"1000.0"
  },
  {
    "Date":"2025-05-19T00:00:00.000",
    "Code":"245A",
    "Open":2499.0,
    "High":2499.0,
    "Low":2498.0,
    "Close":2498.0,
    "UpperLimit":"0",
    "LowerLimit":"0",
    "Volume":900.0,
    "TurnoverValue":"2248400.0",
    "AdjustmentFactor":"1.0",
    "AdjustmentOpen":"2499.0",
    "AdjustmentHigh":"2499.0",
    "AdjustmentLow":"2498.0",
    "AdjustmentClose":"2498.0",
    "AdjustmentVolume":"900.0"
  },
  {
    "Date":"2025-05-20T00:00:00.000",
    "Code":"245A",
    "Open":2448.0,
    "High":2500.0,
    "Low":2448.0,
    "Close":2470.0,
    "UpperLimit":"0",
    "LowerLimit":"0",
    "Volume":1400.0,
    "TurnoverValue":"3481100.0",
    "AdjustmentFactor":"1.0",
    "AdjustmentOpen":"2448.0",
    "AdjustmentHigh":"2500.0",
    "AdjustmentLow":"2448.0",
    "AdjustmentClose":"2470.0",
    "AdjustmentVolume":"1400.0"
  },
  {
    "Date":"2025-05-21T00:00:00.000",
    "Code":"245A",
    "Open":2509.0,
    "High":2509.0,
    "Low":2361.0,
    "Close":2367.0,
    "UpperLimit":"0",
    "LowerLimit":"0",
    "Volume":2800.0,
    "TurnoverValue":"6785000.0",
    "AdjustmentFactor":"1.0",
    "AdjustmentOpen":"2509.0",
    "AdjustmentHigh":"2509.0",
    "AdjustmentLow":"2361.0",
    "AdjustmentClose":"2367.0",
    "AdjustmentVolume":"2800.0"
  },
  {
    "Date":"2025-05-22T00:00:00.000",
    "Code":"245A",
    "Open":2450.0,
    "High":2462.0,
    "Low":2441.0,
    "Close":2441.0,
    "UpperLimit":"0",
    "LowerLimit":"0",
    "Volume":600.0,
    "TurnoverValue":"1469200.0",
    "AdjustmentFactor":"1.0",
    "AdjustmentOpen":"2450.0",
    "AdjustmentHigh":"2462.0",
    "AdjustmentLow":"2441.0",
    "AdjustmentClose":"2441.0",
    "AdjustmentVolume":"600.0"
  },
  {
    "Date":"2025-05-23T00:00:00.000",
    "Code":"245A",
    "Open":2441.0,
    "High":2447.0,
    "Low":2366.0,
    "Close":2366.0,
    "UpperLimit":"0",
    "LowerLimit":"0",
    "Volume":3400.0,
    "TurnoverValue":"8185500.0",
    "AdjustmentFactor":"1.0",
    "AdjustmentOpen":"2441.0",
    "AdjustmentHigh":"2447.0",
    "AdjustmentLow":"2366.0",
    "AdjustmentClose":"2366.0",
    "AdjustmentVolume":"3400.0"
  },
  {
    "Date":"2025-05-26T00:00:00.000",
    "Code":"245A",
    "Open":2416.0,
    "High":2469.0,
    "Low":2416.0,
    "Close":2469.0,
    "UpperLimit":"0",
    "LowerLimit":"0",
    "Volume":4000.0,
    "TurnoverValue":"9727600.0",
    "AdjustmentFactor":"1.0",
    "AdjustmentOpen":"2416.0",
    "AdjustmentHigh":"2469.0",
    "AdjustmentLow":"2416.0",
    "AdjustmentClose":"2469.0",
    "AdjustmentVolume":"4000.0"
  },
  {
    "Date":"2025-05-27T00:00:00.000",
    "Code":"245A",
    "Open":2420.0,
    "High":2519.0,
    "Low":2418.0,
    "Close":2424.0,
    "UpperLimit":"0",
    "LowerLimit":"0",
    "Volume":4500.0,
    "TurnoverValue":"10966500.0",
    "AdjustmentFactor":"1.0",
    "AdjustmentOpen":"2420.0",
    "AdjustmentHigh":"2519.0",
    "AdjustmentLow":"2418.0",
    "AdjustmentClose":"2424.0",
    "AdjustmentVolume":"4500.0"
  },
  {
    "Date":"2025-05-28T00:00:00.000",
    "Code":"245A",
    "Open":2425.0,
    "High":2518.0,
    "Low":2425.0,
    "Close":2440.0,
    "UpperLimit":"0",
    "LowerLimit":"0",
    "Volume":2100.0,
    "TurnoverValue":"5140400.0",
    "AdjustmentFactor":"1.0",
    "AdjustmentOpen":"2425.0",
    "AdjustmentHigh":"2518.0",
    "AdjustmentLow":"2425.0",
    "AdjustmentClose":"2440.0",
    "AdjustmentVolume":"2100.0"
  },
  {
    "Date":"2025-05-29T00:00:00.000",
    "Code":"245A",
    "Open":2433.0,
    "High":2462.0,
    "Low":2348.0,
    "Close":2351.0,
    "UpperLimit":"0",
    "LowerLimit":"0",
    "Volume":5800.0,
    "TurnoverValue":"13986000.0",
    "AdjustmentFactor":"1.0",
    "AdjustmentOpen":"2433.0",
    "AdjustmentHigh":"2462.0",
    "AdjustmentLow":"2348.0",
    "AdjustmentClose":"2351.0",
    "AdjustmentVolume":"5800.0"
  },
  {
    "Date":"2025-05-30T00:00:00.000",
    "Code":"245A",
    "Open":2341.0,
    "High":2425.0,
    "Low":2324.0,
    "Close":2425.0,
    "UpperLimit":"0",
    "LowerLimit":"0",
    "Volume":1300.0,
    "TurnoverValue":"3055400.0",
    "AdjustmentFactor":"1.0",
    "AdjustmentOpen":"2341.0",
    "AdjustmentHigh":"2425.0",
    "AdjustmentLow":"2324.0",
    "AdjustmentClose":"2425.0",
    "AdjustmentVolume":"1300.0"
  },
  {
    "Date":"2025-06-02T00:00:00.000",
    "Code":"245A",
    "Open":2475.0,
    "High":2475.0,
    "Low":2365.0,
    "Close":2459.0,
    "UpperLimit":"0",
    "LowerLimit":"0",
    "Volume":1300.0,
    "TurnoverValue":"3156000.0",
    "AdjustmentFactor":"1.0",
    "AdjustmentOpen":"2475.0",
    "AdjustmentHigh":"2475.0",
    "AdjustmentLow":"2365.0",
    "AdjustmentClose":"2459.0",
    "AdjustmentVolume":"1300.0"
  },
  {
    "Date":"2025-06-03T00:00:00.000",
    "Code":"245A",
    "Open":2476.0,
    "High":2476.0,
    "Low":2401.0,
    "Close":2449.0,
    "UpperLimit":"0",
    "LowerLimit":"0",
    "Volume":1500.0,
    "TurnoverValue":"3663300.0",
    "AdjustmentFactor":"1.0",
    "AdjustmentOpen":"2476.0",
    "AdjustmentHigh":"2476.0",
    "AdjustmentLow":"2401.0",
    "AdjustmentClose":"2449.0",
    "AdjustmentVolume":"1500.0"
  },
  {
    "Date":"2025-06-04T00:00:00.000",
    "Code":"245A",
    "Open":2449.0,
    "High":2449.0,
    "Low":2404.0,
    "Close":2418.0,
    "UpperLimit":"0",
    "LowerLimit":"0",
    "Volume":2000.0,
    "TurnoverValue":"4865100.0",
    "AdjustmentFactor":"1.0",
    "AdjustmentOpen":"2449.0",
    "AdjustmentHigh":"2449.0",
    "AdjustmentLow":"2404.0",
    "AdjustmentClose":"2418.0",
    "AdjustmentVolume":"2000.0"
  },
  {
    "Date":"2025-06-05T00:00:00.000",
    "Code":"245A",
    "Open":2416.0,
    "High":2416.0,
    "Low":2416.0,
    "Close":2416.0,
    "UpperLimit":"0",
    "LowerLimit":"0",
    "Volume":100.0,
    "TurnoverValue":"241600.0",
    "AdjustmentFactor":"1.0",
    "AdjustmentOpen":"2416.0",
    "AdjustmentHigh":"2416.0",
    "AdjustmentLow":"2416.0",
    "AdjustmentClose":"2416.0",
    "AdjustmentVolume":"100.0"
  },
  {
    "Date":"2025-06-06T00:00:00.000",
    "Code":"245A",
    "Open":2415.0,
    "High":2485.0,
    "Low":2415.0,
    "Close":2440.0,
    "UpperLimit":"0",
    "LowerLimit":"0",
    "Volume":1300.0,
    "TurnoverValue":"3181200.0",
    "AdjustmentFactor":"1.0",
    "AdjustmentOpen":"2415.0",
    "AdjustmentHigh":"2485.0",
    "AdjustmentLow":"2415.0",
    "AdjustmentClose":"2440.0",
    "AdjustmentVolume":"1300.0"
  },
  {
    "Date":"2025-06-09T00:00:00.000",
    "Code":"245A",
    "Open":2525.0,
    "High":2577.0,
    "Low":2525.0,
    "Close":2577.0,
    "UpperLimit":"0",
    "LowerLimit":"0",
    "Volume":17800.0,
    "TurnoverValue":"45434900.0",
    "AdjustmentFactor":"1.0",
    "AdjustmentOpen":"2525.0",
    "AdjustmentHigh":"2577.0",
    "AdjustmentLow":"2525.0",
    "AdjustmentClose":"2577.0",
    "AdjustmentVolume":"17800.0"
  },
  {
    "Date":"2025-06-10T00:00:00.000",
    "Code":"245A",
    "Open":2580.0,
    "High":2583.0,
    "Low":2541.0,
    "Close":2546.0,
    "UpperLimit":"0",
    "LowerLimit":"0",
    "Volume":5100.0,
    "TurnoverValue":"13067200.0",
    "AdjustmentFactor":"1.0",
    "AdjustmentOpen":"2580.0",
    "AdjustmentHigh":"2583.0",
    "AdjustmentLow":"2541.0",
    "AdjustmentClose":"2546.0",
    "AdjustmentVolume":"5100.0"
  },
  {
    "Date":"2025-06-11T00:00:00.000",
    "Code":"245A",
    "Open":2550.0,
    "High":2593.0,
    "Low":2540.0,
    "Close":2563.0,
    "UpperLimit":"0",
    "LowerLimit":"0",
    "Volume":5800.0,
    "TurnoverValue":"14887600.0",
    "AdjustmentFactor":"1.0",
    "AdjustmentOpen":"2550.0",
    "AdjustmentHigh":"2593.0",
    "AdjustmentLow":"2540.0",
    "AdjustmentClose":"2563.0",
    "AdjustmentVolume":"5800.0"
  },
  {
    "Date":"2025-06-12T00:00:00.000",
    "Code":"245A",
    "Open":2560.0,
    "High":2574.0,
    "Low":2530.0,
    "Close":2541.0,
    "UpperLimit":"0",
    "LowerLimit":"0",
    "Volume":3100.0,
    "TurnoverValue":"7930800.0",
    "AdjustmentFactor":"1.0",
    "AdjustmentOpen":"2560.0",
    "AdjustmentHigh":"2574.0",
    "AdjustmentLow":"2530.0",
    "AdjustmentClose":"2541.0",
    "AdjustmentVolume":"3100.0"
  },
  {
    "Date":"2025-06-13T00:00:00.000",
    "Code":"245A",
    "Open":2568.0,
    "High":2568.0,
    "Low":2545.0,
    "Close":2555.0,
    "UpperLimit":"0",
    "LowerLimit":"0",
    "Volume":1000.0,
    "TurnoverValue":"2555500.0",
    "AdjustmentFactor":"1.0",
    "AdjustmentOpen":"2568.0",
    "AdjustmentHigh":"2568.0",
    "AdjustmentLow":"2545.0",
    "AdjustmentClose":"2555.0",
    "AdjustmentVolume":"1000.0"
  },
  {
    "Date":"2025-06-16T00:00:00.000",
    "Code":"245A",
    "Open":2576.0,
    "High":2601.0,
    "Low":2553.0,
    "Close":2581.0,
    "UpperLimit":"0",
    "LowerLimit":"0",
    "Volume":3700.0,
    "TurnoverValue":"9556800.0",
    "AdjustmentFactor":"1.0",
    "AdjustmentOpen":"2576.0",
    "AdjustmentHigh":"2601.0",
    "AdjustmentLow":"2553.0",
    "AdjustmentClose":"2581.0",
    "AdjustmentVolume":"3700.0"
  },
  {
    "Date":"2025-06-17T00:00:00.000",
    "Code":"245A",
    "Open":2582.0,
    "High":2608.0,
    "Low":2580.0,
    "Close":2589.0,
    "UpperLimit":"0",
    "LowerLimit":"0",
    "Volume":2200.0,
    "TurnoverValue":"5693900.0",
    "AdjustmentFactor":"1.0",
    "AdjustmentOpen":"2582.0",
    "AdjustmentHigh":"2608.0",
    "AdjustmentLow":"2580.0",
    "AdjustmentClose":"2589.0",
    "AdjustmentVolume":"2200.0"
  },
  {
    "Date":"2025-06-18T00:00:00.000",
    "Code":"245A",
    "Open":2585.0,
    "High":2609.0,
    "Low":2572.0,
    "Close":2591.0,
    "UpperLimit":"0",
    "LowerLimit":"0",
    "Volume":5800.0,
    "TurnoverValue":"15032000.0",
    "AdjustmentFactor":"1.0",
    "AdjustmentOpen":"2585.0",
    "AdjustmentHigh":"2609.0",
    "AdjustmentLow":"2572.0",
    "AdjustmentClose":"2591.0",
    "AdjustmentVolume":"5800.0"
  },
  {
    "Date":"2025-06-19T00:00:00.000",
    "Code":"245A",
    "Open":2607.0,
    "High":2640.0,
    "Low":2601.0,
    "Close":2640.0,
    "UpperLimit":"0",
    "LowerLimit":"0",
    "Volume":4700.0,
    "TurnoverValue":"12297900.0",
    "AdjustmentFactor":"1.0",
    "AdjustmentOpen":"2607.0",
    "AdjustmentHigh":"2640.0",
    "AdjustmentLow":"2601.0",
    "AdjustmentClose":"2640.0",
    "AdjustmentVolume":"4700.0"
  },
  {
    "Date":"2025-06-20T00:00:00.000",
    "Code":"245A",
    "Open":2662.0,
    "High":2698.0,
    "Low":2641.0,
    "Close":2681.0,
    "UpperLimit":"0",
    "LowerLimit":"0",
    "Volume":6900.0,
    "TurnoverValue":"18448700.0",
    "AdjustmentFactor":"1.0",
    "AdjustmentOpen":"2662.0",
    "AdjustmentHigh":"2698.0",
    "AdjustmentLow":"2641.0",
    "AdjustmentClose":"2681.0",
    "AdjustmentVolume":"6900.0"
  },
  {
    "Date":"2025-06-23T00:00:00.000",
    "Code":"245A",
    "Open":2681.0,
    "High":2880.0,
    "Low":2681.0,
    "Close":2880.0,
    "UpperLimit":"0",
    "LowerLimit":"0",
    "Volume":13500.0,
    "TurnoverValue":"37802800.0",
    "AdjustmentFactor":"1.0",
    "AdjustmentOpen":"2681.0",
    "AdjustmentHigh":"2880.0",
    "AdjustmentLow":"2681.0",
    "AdjustmentClose":"2880.0",
    "AdjustmentVolume":"13500.0"
  },
  {
    "Date":"2025-06-24T00:00:00.000",
    "Code":"245A",
    "Open":2965.0,
    "High":2979.0,
    "Low":2830.0,
    "Close":2830.0,
    "UpperLimit":"0",
    "LowerLimit":"0",
    "Volume":8800.0,
    "TurnoverValue":"25621900.0",
    "AdjustmentFactor":"1.0",
    "AdjustmentOpen":"2965.0",
    "AdjustmentHigh":"2979.0",
    "AdjustmentLow":"2830.0",
    "AdjustmentClose":"2830.0",
    "AdjustmentVolume":"8800.0"
  },
  {
    "Date":"2025-06-25T00:00:00.000",
    "Code":"245A",
    "Open":2830.0,
    "High":2975.0,
    "Low":2830.0,
    "Close":2870.0,
    "UpperLimit":"0",
    "LowerLimit":"0",
    "Volume":2700.0,
    "TurnoverValue":"7858900.0",
    "AdjustmentFactor":"1.0",
    "AdjustmentOpen":"2830.0",
    "AdjustmentHigh":"2975.0",
    "AdjustmentLow":"2830.0",
    "AdjustmentClose":"2870.0",
    "AdjustmentVolume":"2700.0"
  },
  {
    "Date":"2025-06-26T00:00:00.000",
    "Code":"245A",
    "Open":2967.0,
    "High":2967.0,
    "Low":2850.0,
    "Close":2851.0,
    "UpperLimit":"0",
    "LowerLimit":"0",
    "Volume":3400.0,
    "TurnoverValue":"9853000.0",
    "AdjustmentFactor":"1.0",
    "AdjustmentOpen":"2967.0",
    "AdjustmentHigh":"2967.0",
    "AdjustmentLow":"2850.0",
    "AdjustmentClose":"2851.0",
    "AdjustmentVolume":"3400.0"
  },
  {
    "Date":"2025-06-27T00:00:00.000",
    "Code":"245A",
    "Open":2841.0,
    "High":2900.0,
    "Low":2775.0,
    "Close":2775.0,
    "UpperLimit":"0",
    "LowerLimit":"0",
    "Volume":7200.0,
    "TurnoverValue":"20238900.0",
    "AdjustmentFactor":"1.0",
    "AdjustmentOpen":"2841.0",
    "AdjustmentHigh":"2900.0",
    "AdjustmentLow":"2775.0",
    "AdjustmentClose":"2775.0",
    "AdjustmentVolume":"7200.0"
  },
  {
    "Date":"2025-06-30T00:00:00.000",
    "Code":"245A",
    "Open":2797.0,
    "High":2797.0,
    "Low":2607.0,
    "Close":2671.0,
    "UpperLimit":"0",
    "LowerLimit":"0",
    "Volume":9900.0,
    "TurnoverValue":"26638600.0",
    "AdjustmentFactor":"1.0",
    "AdjustmentOpen":"2797.0",
    "AdjustmentHigh":"2797.0",
    "AdjustmentLow":"2607.0",
    "AdjustmentClose":"2671.0",
    "AdjustmentVolume":"9900.0"
  },
  {
    "Date":"2025-07-01T00:00:00.000",
    "Code":"245A",
    "Open":2676.0,
    "High":2737.0,
    "Low":2676.0,
    "Close":2691.0,
    "UpperLimit":"0",
    "LowerLimit":"0",
    "Volume":1400.0,
    "TurnoverValue":"3785800.0",
    "AdjustmentFactor":"1.0",
    "AdjustmentOpen":"2676.0",
    "AdjustmentHigh":"2737.0",
    "AdjustmentLow":"2676.0",
    "AdjustmentClose":"2691.0",
    "AdjustmentVolume":"1400.0"
  },
  {
    "Date":"2025-07-02T00:00:00.000",
    "Code":"245A",
    "Open":2677.0,
    "High":2677.0,
    "Low":2611.0,
    "Close":2659.0,
    "UpperLimit":"0",
    "LowerLimit":"0",
    "Volume":3700.0,
    "TurnoverValue":"9778000.0",
    "AdjustmentFactor":"1.0",
    "AdjustmentOpen":"2677.0",
    "AdjustmentHigh":"2677.0",
    "AdjustmentLow":"2611.0",
    "AdjustmentClose":"2659.0",
    "AdjustmentVolume":"3700.0"
  },
  {
    "Date":"2025-07-03T00:00:00.000",
    "Code":"245A",
    "Open":2656.0,
    "High":2656.0,
    "Low":2656.0,
    "Close":2656.0,
    "UpperLimit":"0",
    "LowerLimit":"0",
    "Volume":200.0,
    "TurnoverValue":"531200.0",
    "AdjustmentFactor":"1.0",
    "AdjustmentOpen":"2656.0",
    "AdjustmentHigh":"2656.0",
    "AdjustmentLow":"2656.0",
    "AdjustmentClose":"2656.0",
    "AdjustmentVolume":"200.0"
  },
  {
    "Date":"2025-07-04T00:00:00.000",
    "Code":"245A",
    "Open":2706.0,
    "High":2706.0,
    "Low":2626.0,
    "Close":2641.0,
    "UpperLimit":"0",
    "LowerLimit":"0",
    "Volume":2100.0,
    "TurnoverValue":"5550400.0",
    "AdjustmentFactor":"1.0",
    "AdjustmentOpen":"2706.0",
    "AdjustmentHigh":"2706.0",
    "AdjustmentLow":"2626.0",
    "AdjustmentClose":"2641.0",
    "AdjustmentVolume":"2100.0"
  },
  {
    "Date":"2025-07-07T00:00:00.000",
    "Code":"245A",
    "Open":2641.0,
    "High":2684.0,
    "Low":2608.0,
    "Close":2626.0,
    "UpperLimit":"0",
    "LowerLimit":"0",
    "Volume":4600.0,
    "TurnoverValue":"12201000.0",
    "AdjustmentFactor":"1.0",
    "AdjustmentOpen":"2641.0",
    "AdjustmentHigh":"2684.0",
    "AdjustmentLow":"2608.0",
    "AdjustmentClose":"2626.0",
    "AdjustmentVolume":"4600.0"
  },
  {
    "Date":"2025-07-08T00:00:00.000",
    "Code":"245A",
    "Open":2607.0,
    "High":2644.0,
    "Low":2607.0,
    "Close":2610.0,
    "UpperLimit":"0",
    "LowerLimit":"0",
    "Volume":4400.0,
    "TurnoverValue":"11530000.0",
    "AdjustmentFactor":"1.0",
    "AdjustmentOpen":"2607.0",
    "AdjustmentHigh":"2644.0",
    "AdjustmentLow":"2607.0",
    "AdjustmentClose":"2610.0",
    "AdjustmentVolume":"4400.0"
  },
  {
    "Date":"2025-07-09T00:00:00.000",
    "Code":"245A",
    "Open":2612.0,
    "High":2690.0,
    "Low":2612.0,
    "Close":2677.0,
    "UpperLimit":"0",
    "LowerLimit":"0",
    "Volume":2000.0,
    "TurnoverValue":"5300400.0",
    "AdjustmentFactor":"1.0",
    "AdjustmentOpen":"2612.0",
    "AdjustmentHigh":"2690.0",
    "AdjustmentLow":"2612.0",
    "AdjustmentClose":"2677.0",
    "AdjustmentVolume":"2000.0"
  },
  {
    "Date":"2025-07-10T00:00:00.000",
    "Code":"245A",
    "Open":2638.0,
    "High":2746.0,
    "Low":2615.0,
    "Close":2685.0,
    "UpperLimit":"0",
    "LowerLimit":"0",
    "Volume":3800.0,
    "TurnoverValue":"10102100.0",
    "AdjustmentFactor":"1.0",
    "AdjustmentOpen":"2638.0",
    "AdjustmentHigh":"2746.0",
    "AdjustmentLow":"2615.0",
    "AdjustmentClose":"2685.0",
    "AdjustmentVolume":"3800.0"
  },
  {
    "Date":"2025-07-11T00:00:00.000",
    "Code":"245A",
    "Open":2655.0,
    "High":2670.0,
    "Low":2652.0,
    "Close":2652.0,
    "UpperLimit":"0",
    "LowerLimit":"0",
    "Volume":900.0,
    "TurnoverValue":"2390700.0",
    "AdjustmentFactor":"1.0",
    "AdjustmentOpen":"2655.0",
    "AdjustmentHigh":"2670.0",
    "AdjustmentLow":"2652.0",
    "AdjustmentClose":"2652.0",
    "AdjustmentVolume":"900.0"
  },
  {
    "Date":"2025-07-14T00:00:00.000",
    "Code":"245A",
    "Open":2639.0,
    "High":2645.0,
    "Low":2550.0,
    "Close":2564.0,
    "UpperLimit":"0",
    "LowerLimit":"0",
    "Volume":9600.0,
    "TurnoverValue":"24878100.0",
    "AdjustmentFactor":"1.0",
    "AdjustmentOpen":"2639.0",
    "AdjustmentHigh":"2645.0",
    "AdjustmentLow":"2550.0",
    "AdjustmentClose":"2564.0",
    "AdjustmentVolume":"9600.0"
  },
  {
    "Date":"2025-07-15T00:00:00.000",
    "Code":"245A",
    "Open":2714.0,
    "High":2950.0,
    "Low":2710.0,
    "Close":2950.0,
    "UpperLimit":"0",
    "LowerLimit":"0",
    "Volume":43900.0,
    "TurnoverValue":"125637700.0",
    "AdjustmentFactor":"1.0",
    "AdjustmentOpen":"2714.0",
    "AdjustmentHigh":"2950.0",
    "AdjustmentLow":"2710.0",
    "AdjustmentClose":"2950.0",
    "AdjustmentVolume":"43900.0"
  },
  {
    "Date":"2025-07-16T00:00:00.000",
    "Code":"245A",
    "Open":2900.0,
    "High":2950.0,
    "Low":2818.0,
    "Close":2943.0,
    "UpperLimit":"0",
    "LowerLimit":"0",
    "Volume":6600.0,
    "TurnoverValue":"19043100.0",
    "AdjustmentFactor":"1.0",
    "AdjustmentOpen":"2900.0",
    "AdjustmentHigh":"2950.0",
    "AdjustmentLow":"2818.0",
    "AdjustmentClose":"2943.0",
    "AdjustmentVolume":"6600.0"
  },
  {
    "Date":"2025-07-17T00:00:00.000",
    "Code":"245A",
    "Open":2943.0,
    "High":2956.0,
    "Low":2831.0,
    "Close":2956.0,
    "UpperLimit":"0",
    "LowerLimit":"0",
    "Volume":5700.0,
    "TurnoverValue":"16581200.0",
    "AdjustmentFactor":"1.0",
    "AdjustmentOpen":"2943.0",
    "AdjustmentHigh":"2956.0",
    "AdjustmentLow":"2831.0",
    "AdjustmentClose":"2956.0",
    "AdjustmentVolume":"5700.0"
  },
  {
    "Date":"2025-07-18T00:00:00.000",
    "Code":"245A",
    "Open":2956.0,
    "High":2956.0,
    "Low":2846.0,
    "Close":2918.0,
    "UpperLimit":"0",
    "LowerLimit":"0",
    "Volume":2100.0,
    "TurnoverValue":"6089200.0",
    "AdjustmentFactor":"1.0",
    "AdjustmentOpen":"2956.0",
    "AdjustmentHigh":"2956.0",
    "AdjustmentLow":"2846.0",
    "AdjustmentClose":"2918.0",
    "AdjustmentVolume":"2100.0"
  },
  {
    "Date":"2025-07-22T00:00:00.000",
    "Code":"245A",
    "Open":2918.0,
    "High":2939.0,
    "Low":2860.0,
    "Close":2909.0,
    "UpperLimit":"0",
    "LowerLimit":"0",
    "Volume":3100.0,
    "TurnoverValue":"8991500.0",
    "AdjustmentFactor":"1.0",
    "AdjustmentOpen":"2918.0",
    "AdjustmentHigh":"2939.0",
    "AdjustmentLow":"2860.0",
    "AdjustmentClose":"2909.0",
    "AdjustmentVolume":"3100.0"
  },
  {
    "Date":"2025-07-23T00:00:00.000",
    "Code":"245A",
    "Open":2910.0,
    "High":2910.0,
    "Low":2851.0,
    "Close":2901.0,
    "UpperLimit":"0",
    "LowerLimit":"0",
    "Volume":3500.0,
    "TurnoverValue":"10099200.0",
    "AdjustmentFactor":"1.0",
    "AdjustmentOpen":"2910.0",
    "AdjustmentHigh":"2910.0",
    "AdjustmentLow":"2851.0",
    "AdjustmentClose":"2901.0",
    "AdjustmentVolume":"3500.0"
  },
  {
    "Date":"2025-07-24T00:00:00.000",
    "Code":"245A",
    "Open":2851.0,
    "High":2940.0,
    "Low":2816.0,
    "Close":2900.0,
    "UpperLimit":"0",
    "LowerLimit":"0",
    "Volume":6000.0,
    "TurnoverValue":"17327100.0",
    "AdjustmentFactor":"1.0",
    "AdjustmentOpen":"2851.0",
    "AdjustmentHigh":"2940.0",
    "AdjustmentLow":"2816.0",
    "AdjustmentClose":"2900.0",
    "AdjustmentVolume":"6000.0"
  },
  {
    "Date":"2025-07-25T00:00:00.000",
    "Code":"245A",
    "Open":2950.0,
    "High":3190.0,
    "Low":2950.0,
    "Close":3190.0,
    "UpperLimit":"0",
    "LowerLimit":"0",
    "Volume":6900.0,
    "TurnoverValue":"20758100.0",
    "AdjustmentFactor":"1.0",
    "AdjustmentOpen":"2950.0",
    "AdjustmentHigh":"3190.0",
    "AdjustmentLow":"2950.0",
    "AdjustmentClose":"3190.0",
    "AdjustmentVolume":"6900.0"
  },
  {
    "Date":"2025-07-28T00:00:00.000",
    "Code":"245A",
    "Open":3120.0,
    "High":3295.0,
    "Low":3080.0,
    "Close":3140.0,
    "UpperLimit":"0",
    "LowerLimit":"0",
    "Volume":15800.0,
    "TurnoverValue":"49947500.0",
    "AdjustmentFactor":"1.0",
    "AdjustmentOpen":"3120.0",
    "AdjustmentHigh":"3295.0",
    "AdjustmentLow":"3080.0",
    "AdjustmentClose":"3140.0",
    "AdjustmentVolume":"15800.0"
  },
  {
    "Date":"2025-07-29T00:00:00.000",
    "Code":"245A",
    "Open":3210.0,
    "High":3210.0,
    "Low":3140.0,
    "Close":3175.0,
    "UpperLimit":"0",
    "LowerLimit":"0",
    "Volume":2500.0,
    "TurnoverValue":"7947000.0",
    "AdjustmentFactor":"1.0",
    "AdjustmentOpen":"3210.0",
    "AdjustmentHigh":"3210.0",
    "AdjustmentLow":"3140.0",
    "AdjustmentClose":"3175.0",
    "AdjustmentVolume":"2500.0"
  },
  {
    "Date":"2025-07-30T00:00:00.000",
    "Code":"245A",
    "Open":3175.0,
    "High":3215.0,
    "Low":3115.0,
    "Close":3150.0,
    "UpperLimit":"0",
    "LowerLimit":"0",
    "Volume":2700.0,
    "TurnoverValue":"8521000.0",
    "AdjustmentFactor":"1.0",
    "AdjustmentOpen":"3175.0",
    "AdjustmentHigh":"3215.0",
    "AdjustmentLow":"3115.0",
    "AdjustmentClose":"3150.0",
    "AdjustmentVolume":"2700.0"
  },
  {
    "Date":"2025-07-31T00:00:00.000",
    "Code":"245A",
    "Open":3180.0,
    "High":3400.0,
    "Low":3180.0,
    "Close":3295.0,
    "UpperLimit":"0",
    "LowerLimit":"0",
    "Volume":7500.0,
    "TurnoverValue":"24668000.0",
    "AdjustmentFactor":"1.0",
    "AdjustmentOpen":"3180.0",
    "AdjustmentHigh":"3400.0",
    "AdjustmentLow":"3180.0",
    "AdjustmentClose":"3295.0",
    "AdjustmentVolume":"7500.0"
  },
  {
    "Date":"2025-08-01T00:00:00.000",
    "Code":"245A",
    "Open":3300.0,
    "High":3385.0,
    "Low":3200.0,
    "Close":3255.0,
    "UpperLimit":"0",
    "LowerLimit":"0",
    "Volume":6200.0,
    "TurnoverValue":"20263500.0",
    "AdjustmentFactor":"1.0",
    "AdjustmentOpen":"3300.0",
    "AdjustmentHigh":"3385.0",
    "AdjustmentLow":"3200.0",
    "AdjustmentClose":"3255.0",
    "AdjustmentVolume":"6200.0"
  },
  {
    "Date":"2025-08-04T00:00:00.000",
    "Code":"245A",
    "Open":3225.0,
    "High":3300.0,
    "Low":3200.0,
    "Close":3295.0,
    "UpperLimit":"0",
    "LowerLimit":"0",
    "Volume":3300.0,
    "TurnoverValue":"10723000.0",
    "AdjustmentFactor":"1.0",
    "AdjustmentOpen":"3225.0",
    "AdjustmentHigh":"3300.0",
    "AdjustmentLow":"3200.0",
    "AdjustmentClose":"3295.0",
    "AdjustmentVolume":"3300.0"
  },
  {
    "Date":"2025-08-05T00:00:00.000",
    "Code":"245A",
    "Open":3255.0,
    "High":3500.0,
    "Low":3255.0,
    "Close":3490.0,
    "UpperLimit":"0",
    "LowerLimit":"0",
    "Volume":6100.0,
    "TurnoverValue":"20601000.0",
    "AdjustmentFactor":"1.0",
    "AdjustmentOpen":"3255.0",
    "AdjustmentHigh":"3500.0",
    "AdjustmentLow":"3255.0",
    "AdjustmentClose":"3490.0",
    "AdjustmentVolume":"6100.0"
  },
  {
    "Date":"2025-08-06T00:00:00.000",
    "Code":"245A",
    "Open":3500.0,
    "High":3515.0,
    "Low":3425.0,
    "Close":3440.0,
    "UpperLimit":"0",
    "LowerLimit":"0",
    "Volume":5200.0,
    "TurnoverValue":"18027000.0",
    "AdjustmentFactor":"1.0",
    "AdjustmentOpen":"3500.0",
    "AdjustmentHigh":"3515.0",
    "AdjustmentLow":"3425.0",
    "AdjustmentClose":"3440.0",
    "AdjustmentVolume":"5200.0"
  },
  {
    "Date":"2025-08-07T00:00:00.000",
    "Code":"245A",
    "Open":3425.0,
    "High":3650.0,
    "Low":3425.0,
    "Close":3630.0,
    "UpperLimit":"0",
    "LowerLimit":"0",
    "Volume":5900.0,
    "TurnoverValue":"21009500.0",
    "AdjustmentFactor":"1.0",
    "AdjustmentOpen":"3425.0",
    "AdjustmentHigh":"3650.0",
    "AdjustmentLow":"3425.0",
    "AdjustmentClose":"3630.0",
    "AdjustmentVolume":"5900.0"
  },
  {
    "Date":"2025-08-08T00:00:00.000",
    "Code":"245A",
    "Open":3695.0,
    "High":3720.0,
    "Low":3270.0,
    "Close":3385.0,
    "UpperLimit":"0",
    "LowerLimit":"0",
    "Volume":36300.0,
    "TurnoverValue":"123083500.0",
    "AdjustmentFactor":"1.0",
    "AdjustmentOpen":"3695.0",
    "AdjustmentHigh":"3720.0",
    "AdjustmentLow":"3270.0",
    "AdjustmentClose":"3385.0",
    "AdjustmentVolume":"36300.0"
  },
  {
    "Date":"2025-08-12T00:00:00.000",
    "Code":"245A",
    "Open":3385.0,
    "High":3445.0,
    "Low":3250.0,
    "Close":3255.0,
    "UpperLimit":"0",
    "LowerLimit":"0",
    "Volume":9900.0,
    "TurnoverValue":"33054500.0",
    "AdjustmentFactor":"1.0",
    "AdjustmentOpen":"3385.0",
    "AdjustmentHigh":"3445.0",
    "AdjustmentLow":"3250.0",
    "AdjustmentClose":"3255.0",
    "AdjustmentVolume":"9900.0"
  },
  {
    "Date":"2025-08-13T00:00:00.000",
    "Code":"245A",
    "Open":3215.0,
    "High":3285.0,
    "Low":3105.0,
    "Close":3240.0,
    "UpperLimit":"0",
    "LowerLimit":"0",
    "Volume":13600.0,
    "TurnoverValue":"43038500.0",
    "AdjustmentFactor":"1.0",
    "AdjustmentOpen":"3215.0",
    "AdjustmentHigh":"3285.0",
    "AdjustmentLow":"3105.0",
    "AdjustmentClose":"3240.0",
    "AdjustmentVolume":"13600.0"
  },
  {
    "Date":"2025-08-14T00:00:00.000",
    "Code":"245A",
    "Open":3225.0,
    "High":3225.0,
    "Low":3040.0,
    "Close":3120.0,
    "UpperLimit":"0",
    "LowerLimit":"0",
    "Volume":14900.0,
    "TurnoverValue":"46075500.0",
    "AdjustmentFactor":"1.0",
    "AdjustmentOpen":"3225.0",
    "AdjustmentHigh":"3225.0",
    "AdjustmentLow":"3040.0",
    "AdjustmentClose":"3120.0",
    "AdjustmentVolume":"14900.0"
  },
  {
    "Date":"2025-08-15T00:00:00.000",
    "Code":"245A",
    "Open":3120.0,
    "High":3435.0,
    "Low":3120.0,
    "Close":3320.0,
    "UpperLimit":"0",
    "LowerLimit":"0",
    "Volume":12700.0,
    "TurnoverValue":"41971500.0",
    "AdjustmentFactor":"1.0",
    "AdjustmentOpen":"3120.0",
    "AdjustmentHigh":"3435.0",
    "AdjustmentLow":"3120.0",
    "AdjustmentClose":"3320.0",
    "AdjustmentVolume":"12700.0"
  },
  {
    "Date":"2025-08-18T00:00:00.000",
    "Code":"245A",
    "Open":3450.0,
    "High":3650.0,
    "Low":3300.0,
    "Close":3360.0,
    "UpperLimit":"0",
    "LowerLimit":"0",
    "Volume":16700.0,
    "TurnoverValue":"57795000.0",
    "AdjustmentFactor":"1.0",
    "AdjustmentOpen":"3450.0",
    "AdjustmentHigh":"3650.0",
    "AdjustmentLow":"3300.0",
    "AdjustmentClose":"3360.0",
    "AdjustmentVolume":"16700.0"
  },
  {
    "Date":"2025-08-19T00:00:00.000",
    "Code":"245A",
    "Open":3290.0,
    "High":3320.0,
    "Low":3170.0,
    "Close":3280.0,
    "UpperLimit":"0",
    "LowerLimit":"0",
    "Volume":11800.0,
    "TurnoverValue":"38096500.0",
    "AdjustmentFactor":"1.0",
    "AdjustmentOpen":"3290.0",
    "AdjustmentHigh":"3320.0",
    "AdjustmentLow":"3170.0",
    "AdjustmentClose":"3280.0",
    "AdjustmentVolume":"11800.0"
  },
  {
    "Date":"2025-08-20T00:00:00.000",
    "Code":"245A",
    "Open":3275.0,
    "High":3305.0,
    "Low":3205.0,
    "Close":3205.0,
    "UpperLimit":"0",
    "LowerLimit":"0",
    "Volume":4400.0,
    "TurnoverValue":"14318500.0",
    "AdjustmentFactor":"1.0",
    "AdjustmentOpen":"3275.0",
    "AdjustmentHigh":"3305.0",
    "AdjustmentLow":"3205.0",
    "AdjustmentClose":"3205.0",
    "AdjustmentVolume":"4400.0"
  },
  {
    "Date":"2025-08-21T00:00:00.000",
    "Code":"245A",
    "Open":3205.0,
    "High":3245.0,
    "Low":3110.0,
    "Close":3175.0,
    "UpperLimit":"0",
    "LowerLimit":"0",
    "Volume":5600.0,
    "TurnoverValue":"17765500.0",
    "AdjustmentFactor":"1.0",
    "AdjustmentOpen":"3205.0",
    "AdjustmentHigh":"3245.0",
    "AdjustmentLow":"3110.0",
    "AdjustmentClose":"3175.0",
    "AdjustmentVolume":"5600.0"
  },
  {
    "Date":"2025-08-22T00:00:00.000",
    "Code":"245A",
    "Open":3245.0,
    "High":3245.0,
    "Low":3070.0,
    "Close":3070.0,
    "UpperLimit":"0",
    "LowerLimit":"0",
    "Volume":7800.0,
    "TurnoverValue":"24498000.0",
    "AdjustmentFactor":"1.0",
    "AdjustmentOpen":"3245.0",
    "AdjustmentHigh":"3245.0",
    "AdjustmentLow":"3070.0",
    "AdjustmentClose":"3070.0",
    "AdjustmentVolume":"7800.0"
  },
  {
    "Date":"2025-08-25T00:00:00.000",
    "Code":"245A",
    "Open":3075.0,
    "High":3155.0,
    "Low":3040.0,
    "Close":3080.0,
    "UpperLimit":"0",
    "LowerLimit":"0",
    "Volume":10400.0,
    "TurnoverValue":"32232500.0",
    "AdjustmentFactor":"1.0",
    "AdjustmentOpen":"3075.0",
    "AdjustmentHigh":"3155.0",
    "AdjustmentLow":"3040.0",
    "AdjustmentClose":"3080.0",
    "AdjustmentVolume":"10400.0"
  },
  {
    "Date":"2025-08-26T00:00:00.000",
    "Code":"245A",
    "Open":3075.0,
    "High":3215.0,
    "Low":3075.0,
    "Close":3145.0,
    "UpperLimit":"0",
    "LowerLimit":"0",
    "Volume":6900.0,
    "TurnoverValue":"21616000.0",
    "AdjustmentFactor":"1.0",
    "AdjustmentOpen":"3075.0",
    "AdjustmentHigh":"3215.0",
    "AdjustmentLow":"3075.0",
    "AdjustmentClose":"3145.0",
    "AdjustmentVolume":"6900.0"
  },
  {
    "Date":"2025-08-27T00:00:00.000",
    "Code":"245A",
    "Open":3145.0,
    "High":3195.0,
    "Low":3080.0,
    "Close":3105.0,
    "UpperLimit":"0",
    "LowerLimit":"0",
    "Volume":7900.0,
    "TurnoverValue":"24684000.0",
    "AdjustmentFactor":"1.0",
    "AdjustmentOpen":"3145.0",
    "AdjustmentHigh":"3195.0",
    "AdjustmentLow":"3080.0",
    "AdjustmentClose":"3105.0",
    "AdjustmentVolume":"7900.0"
  },
  {
    "Date":"2025-08-28T00:00:00.000",
    "Code":"245A",
    "Open":3095.0,
    "High":3130.0,
    "Low":3035.0,
    "Close":3060.0,
    "UpperLimit":"0",
    "LowerLimit":"0",
    "Volume":6500.0,
    "TurnoverValue":"20069500.0",
    "AdjustmentFactor":"1.0",
    "AdjustmentOpen":"3095.0",
    "AdjustmentHigh":"3130.0",
    "AdjustmentLow":"3035.0",
    "AdjustmentClose":"3060.0",
    "AdjustmentVolume":"6500.0"
  },
  {
    "Date":"2025-08-29T00:00:00.000",
    "Code":"245A",
    "Open":3095.0,
    "High":3205.0,
    "Low":3060.0,
    "Close":3100.0,
    "UpperLimit":"0",
    "LowerLimit":"0",
    "Volume":6900.0,
    "TurnoverValue":"21575500.0",
    "AdjustmentFactor":"1.0",
    "AdjustmentOpen":"3095.0",
    "AdjustmentHigh":"3205.0",
    "AdjustmentLow":"3060.0",
    "AdjustmentClose":"3100.0",
    "AdjustmentVolume":"6900.0"
  },
  {
    "Date":"2025-09-01T00:00:00.000",
    "Code":"245A",
    "Open":3110.0,
    "High":3130.0,
    "Low":3010.0,
    "Close":3065.0,
    "UpperLimit":"0",
    "LowerLimit":"0",
    "Volume":8800.0,
    "TurnoverValue":"27024500.0",
    "AdjustmentFactor":"1.0",
    "AdjustmentOpen":"3110.0",
    "AdjustmentHigh":"3130.0",
    "AdjustmentLow":"3010.0",
    "AdjustmentClose":"3065.0",
    "AdjustmentVolume":"8800.0"
  },
  {
    "Date":"2025-09-02T00:00:00.000",
    "Code":"245A",
    "Open":3030.0,
    "High":3070.0,
    "Low":3020.0,
    "Close":3070.0,
    "UpperLimit":"0",
    "LowerLimit":"0",
    "Volume":4000.0,
    "TurnoverValue":"12233500.0",
    "AdjustmentFactor":"1.0",
    "AdjustmentOpen":"3030.0",
    "AdjustmentHigh":"3070.0",
    "AdjustmentLow":"3020.0",
    "AdjustmentClose":"3070.0",
    "AdjustmentVolume":"4000.0"
  },
  {
    "Date":"2025-09-03T00:00:00.000",
    "Code":"245A",
    "Open":3070.0,
    "High":3070.0,
    "Low":3050.0,
    "Close":3070.0,
    "UpperLimit":"0",
    "LowerLimit":"0",
    "Volume":800.0,
    "TurnoverValue":"2445500.0",
    "AdjustmentFactor":"1.0",
    "AdjustmentOpen":"3070.0",
    "AdjustmentHigh":"3070.0",
    "AdjustmentLow":"3050.0",
    "AdjustmentClose":"3070.0",
    "AdjustmentVolume":"800.0"
  },
  {
    "Date":"2025-09-04T00:00:00.000",
    "Code":"245A",
    "Open":3040.0,
    "High":3075.0,
    "Low":3035.0,
    "Close":3075.0,
    "UpperLimit":"0",
    "LowerLimit":"0",
    "Volume":2100.0,
    "TurnoverValue":"6404500.0",
    "AdjustmentFactor":"1.0",
    "AdjustmentOpen":"3040.0",
    "AdjustmentHigh":"3075.0",
    "AdjustmentLow":"3035.0",
    "AdjustmentClose":"3075.0",
    "AdjustmentVolume":"2100.0"
  },
  {
    "Date":"2025-09-05T00:00:00.000",
    "Code":"245A",
    "Open":3100.0,
    "High":3175.0,
    "Low":3100.0,
    "Close":3175.0,
    "UpperLimit":"0",
    "LowerLimit":"0",
    "Volume":4500.0,
    "TurnoverValue":"14035500.0",
    "AdjustmentFactor":"1.0",
    "AdjustmentOpen":"3100.0",
    "AdjustmentHigh":"3175.0",
    "AdjustmentLow":"3100.0",
    "AdjustmentClose":"3175.0",
    "AdjustmentVolume":"4500.0"
  }
]